{"path":"%D0%9C%D0%BE%D1%80%D0%B8%D0%BD%D0%B0%20%D0%B4%D0%BB%D0%B8%D0%BD%D0%BD%D0%BE%D0%BB%D0%B8%D1%81%D1%82%D0%BD%D0%B0%D1%8F%20-%20Morina%20longifolia","deepCounters":{"total":13,"images":13,"files":13},"counters":{"total":13,"images":13,"files":13},"thumb":{"path":"thumbs\/DSC04908.webp","width":512,"height":410},"thumbCaption":"<h3>Морина длиннолистная - Morina longifolia<\/h3>","album":{"description":"<br\/>\nHerbarium.INFO Herbarium Photo Collection: Ferns, Conifers, Cycads, Flowers, Trees, Mosses, Grasses, Pests and Diseases.<br\/>\n<br\/><i><b>3209<\/b> species in <b>221<\/b> families and in <b>66<\/b> orders photographed.<br\/>\n<br\/><b>39103<\/b> images total.<\/i><br\/><br\/>\nTry also other sites: <br\/>\n    <a href=\"https:\/\/herbariuminfo.netlify.app\">Herbarium.INFO<\/a>&nbsp;\u2022&nbsp;\n     <a href=\"https:\/\/plantariuminfo.netlify.app\">Plantarium.INFO<\/a>&nbsp;\u2022&nbsp;\n    <a href=\"https:\/\/fungarium.netlify.app\">Fungarium.INFO<\/a>&nbsp;\u2022&nbsp;\n    <a href=\"https:\/\/lichenarium.netlify.app\">Lichenarium.INFO<\/a>&nbsp;\u2022&nbsp;\n    <a href=\"https:\/\/algaerium.netlify.app\">Algaerium.INFO<\/a>","title":"Herbarium.INFO Herbs: Dicotyledones & Monocotyledones"},"objects":[{"image":{"path":"slides\/DSC04908.webp","width":2000,"height":1500},"thumb":{"path":"thumbs\/DSC04908.webp","width":512,"height":410},"thumbCaption":"<span class=\"nr\">1<\/span><div class=\"title\">DSC04908<\/div>","photodata":"<b>Original Date<\/b> <i>7\/25\/22, 12:09\u202FPM<\/i> &middot; <b>Make<\/b> <i>SONY<\/i> &middot; <b>Camera<\/b> <i>DSC-HX99<\/i> &middot; <b>Lens<\/b> <i>4.25-118mm f\/3.5-6.4<\/i> &middot; <b>Focal Length (35mm)<\/b> <i>62mm<\/i> &middot; <b>Metering Mode<\/b> <i>Multi-segment<\/i> &middot; <b>ISO Equivalent<\/b> <i>200<\/i> &middot; <b>Exposure Time<\/b> <i>1\/160s<\/i> &middot; <b>Aperture<\/b> <i>ƒ\/4.5<\/i> &middot; <b>Exposure bias<\/b> <i>0 EV<\/i> &middot; <b>Exposure Program<\/b> <i>Manual control<\/i> &middot; <b>White balance<\/b> <i>Manual white balance<\/i> &middot; <b>Flash<\/b> <i>Flash did not fire<\/i> &middot; <b>Resolution<\/b> <i>4896 x 3672<\/i>","dates":{"added":1658856647,"dateTaken":1658740161},"fileDate":"2022-07-25T12:09:20.0Z","path":"DSC04908.webp","imageCaption":"<div class=\"title\">DSC04908<\/div>","fileSize":13892709,"name":"DSC04908.webp","comment":"                               ","category":"image","camera":{"aperture":4.5,"exposureTime":"1\/160s","originalDate":"2022-07-25T12:09:21.0Z","cameraModel":"DSC-HX99","focalLength35mm":"62mm","resolution":"4896 x 3672","cameraMake":"SONY","isoEquivalent":200,"flash":"Flash did not fire","focalLength":"10mm"}},{"image":{"path":"slides\/DSC04909.webp","width":1500,"height":2000},"thumb":{"path":"thumbs\/DSC04909.webp","width":512,"height":410},"thumbCaption":"<span class=\"nr\">2<\/span><div class=\"title\">DSC04909<\/div>","photodata":"<b>Original Date<\/b> <i>7\/25\/22, 12:09\u202FPM<\/i> &middot; <b>Make<\/b> <i>SONY<\/i> &middot; <b>Camera<\/b> <i>DSC-HX99<\/i> &middot; <b>Lens<\/b> <i>4.25-118mm f\/3.5-6.4<\/i> &middot; <b>Focal Length (35mm)<\/b> <i>28mm<\/i> &middot; <b>Metering Mode<\/b> <i>Multi-segment<\/i> &middot; <b>ISO Equivalent<\/b> <i>200<\/i> &middot; <b>Exposure Time<\/b> <i>1\/160s<\/i> &middot; <b>Aperture<\/b> <i>ƒ\/4<\/i> &middot; <b>Exposure bias<\/b> <i>0 EV<\/i> &middot; <b>Exposure Program<\/b> <i>Manual control<\/i> &middot; <b>White balance<\/b> <i>Manual white balance<\/i> &middot; <b>Flash<\/b> <i>Flash did not fire<\/i> &middot; <b>Resolution<\/b> <i>4896 x 3672<\/i>","dates":{"added":1658856647,"dateTaken":1658740166},"fileDate":"2022-07-25T12:09:26.0Z","path":"DSC04909.webp","imageCaption":"<div class=\"title\">DSC04909<\/div>","fileSize":17146508,"name":"DSC04909.webp","comment":"                               ","location":"57.643919,18.295151","category":"image","camera":{"aperture":4.0,"exposureTime":"1\/160s","originalDate":"2022-07-25T12:09:26.0Z","cameraModel":"DSC-HX99","location":{"latitude":"57° 38' 38.11\"","lat":57.64392,"long":18.29515,"longitude":"18° 17' 42.54\""},"focalLength35mm":"28mm","resolution":"4896 x 3672","cameraMake":"SONY","isoEquivalent":200,"flash":"Flash did not fire","focalLength":"5mm"}},{"image":{"path":"slides\/DSC09061.webp","width":1500,"height":2000},"thumb":{"path":"thumbs\/DSC09061.webp","width":512,"height":410},"thumbCaption":"<span class=\"nr\">3<\/span><div class=\"title\">DSC09061<\/div>","photodata":"<b>Original Date<\/b> <i>7\/6\/20, 1:53\u202FPM<\/i> &middot; <b>Make<\/b> <i>SONY<\/i> &middot; <b>Camera<\/b> <i>DSC-HX90V<\/i> &middot; <b>Lens<\/b> <i>4.1-123mm f\/3.5-6.4<\/i> &middot; <b>Focal Length (35mm)<\/b> <i>24mm<\/i> &middot; <b>Metering Mode<\/b> <i>Multi-segment<\/i> &middot; <b>ISO Equivalent<\/b> <i>200<\/i> &middot; <b>Exposure Time<\/b> <i>1\/320s<\/i> &middot; <b>Aperture<\/b> <i>ƒ\/3.5<\/i> &middot; <b>Exposure bias<\/b> <i>0 EV<\/i> &middot; <b>Exposure Program<\/b> <i>Manual control<\/i> &middot; <b>White balance<\/b> <i>Manual white balance<\/i> &middot; <b>Flash<\/b> <i>Flash did not fire<\/i> &middot; <b>Resolution<\/b> <i>4896 x 3672<\/i>","dates":{"added":1594237350,"dateTaken":1594032813},"fileDate":"2020-07-06T13:53:32.0Z","path":"DSC09061.webp","imageCaption":"<div class=\"title\">DSC09061<\/div>","fileSize":6960070,"name":"DSC09061.webp","comment":"                               ","location":"58.384395,26.720630","category":"image","camera":{"aperture":3.5,"exposureTime":"1\/320s","originalDate":"2020-07-06T13:53:33.0Z","cameraModel":"DSC-HX90V","location":{"altitude":"36.4 metres","latitude":"58° 23' 3.82\"","lat":58.384396,"long":26.72063,"longitude":"26° 43' 14.27\""},"focalLength35mm":"24mm","resolution":"4896 x 3672","cameraMake":"SONY","isoEquivalent":200,"flash":"Flash did not fire","focalLength":"4mm"}},{"image":{"path":"slides\/DSC09062.webp","width":1500,"height":2000},"thumb":{"path":"thumbs\/DSC09062.webp","width":512,"height":410},"thumbCaption":"<span class=\"nr\">4<\/span><div class=\"title\">DSC09062<\/div>","photodata":"<b>Original Date<\/b> <i>7\/6\/20, 1:53\u202FPM<\/i> &middot; <b>Make<\/b> <i>SONY<\/i> &middot; <b>Camera<\/b> <i>DSC-HX90V<\/i> &middot; <b>Lens<\/b> <i>4.1-123mm f\/3.5-6.4<\/i> &middot; <b>Focal Length (35mm)<\/b> <i>24mm<\/i> &middot; <b>Metering Mode<\/b> <i>Multi-segment<\/i> &middot; <b>ISO Equivalent<\/b> <i>200<\/i> &middot; <b>Exposure Time<\/b> <i>1\/250s<\/i> &middot; <b>Aperture<\/b> <i>ƒ\/3.5<\/i> &middot; <b>Exposure bias<\/b> <i>0 EV<\/i> &middot; <b>Exposure Program<\/b> <i>Manual control<\/i> &middot; <b>White balance<\/b> <i>Manual white balance<\/i> &middot; <b>Flash<\/b> <i>Flash did not fire<\/i> &middot; <b>Resolution<\/b> <i>4896 x 3672<\/i>","dates":{"added":1594237350,"dateTaken":1594032823},"fileDate":"2020-07-06T13:53:42.0Z","path":"DSC09062.webp","imageCaption":"<div class=\"title\">DSC09062<\/div>","fileSize":7564850,"name":"DSC09062.webp","comment":"                               ","location":"58.384373,26.720636","category":"image","camera":{"aperture":3.5,"exposureTime":"1\/250s","originalDate":"2020-07-06T13:53:43.0Z","cameraModel":"DSC-HX90V","location":{"altitude":"37.1 metres","latitude":"58° 23' 3.74\"","lat":58.384373,"long":26.720636,"longitude":"26° 43' 14.29\""},"focalLength35mm":"24mm","resolution":"4896 x 3672","cameraMake":"SONY","isoEquivalent":200,"flash":"Flash did not fire","focalLength":"4mm"}},{"image":{"path":"slides\/DSC09063.webp","width":1500,"height":2000},"thumb":{"path":"thumbs\/DSC09063.webp","width":512,"height":410},"thumbCaption":"<span class=\"nr\">5<\/span><div class=\"title\">DSC09063<\/div>","photodata":"<b>Original Date<\/b> <i>7\/6\/20, 1:53\u202FPM<\/i> &middot; <b>Make<\/b> <i>SONY<\/i> &middot; <b>Camera<\/b> <i>DSC-HX90V<\/i> &middot; <b>Lens<\/b> <i>4.1-123mm f\/3.5-6.4<\/i> &middot; <b>Focal Length (35mm)<\/b> <i>24mm<\/i> &middot; <b>Metering Mode<\/b> <i>Multi-segment<\/i> &middot; <b>ISO Equivalent<\/b> <i>200<\/i> &middot; <b>Exposure Time<\/b> <i>1\/160s<\/i> &middot; <b>Aperture<\/b> <i>ƒ\/3.5<\/i> &middot; <b>Exposure bias<\/b> <i>0 EV<\/i> &middot; <b>Exposure Program<\/b> <i>Manual control<\/i> &middot; <b>White balance<\/b> <i>Manual white balance<\/i> &middot; <b>Flash<\/b> <i>Flash did not fire<\/i> &middot; <b>Resolution<\/b> <i>4896 x 3672<\/i>","dates":{"added":1594237350,"dateTaken":1594032830},"fileDate":"2020-07-06T13:53:50.0Z","path":"DSC09063.webp","imageCaption":"<div class=\"title\">DSC09063<\/div>","fileSize":7738663,"name":"DSC09063.webp","comment":"                               ","location":"58.384370,26.720616","category":"image","camera":{"aperture":3.5,"exposureTime":"1\/160s","originalDate":"2020-07-06T13:53:50.0Z","cameraModel":"DSC-HX90V","location":{"altitude":"37.7 metres","latitude":"58° 23' 3.73\"","lat":58.38437,"long":26.720615,"longitude":"26° 43' 14.22\""},"focalLength35mm":"24mm","resolution":"4896 x 3672","cameraMake":"SONY","isoEquivalent":200,"flash":"Flash did not fire","focalLength":"4mm"}},{"image":{"path":"slides\/DSC09064.webp","width":1500,"height":2000},"thumb":{"path":"thumbs\/DSC09064.webp","width":512,"height":410},"thumbCaption":"<span class=\"nr\">6<\/span><div class=\"title\">DSC09064<\/div>","photodata":"<b>Original Date<\/b> <i>7\/6\/20, 1:53\u202FPM<\/i> &middot; <b>Make<\/b> <i>SONY<\/i> &middot; <b>Camera<\/b> <i>DSC-HX90V<\/i> &middot; <b>Lens<\/b> <i>4.1-123mm f\/3.5-6.4<\/i> &middot; <b>Focal Length (35mm)<\/b> <i>24mm<\/i> &middot; <b>Metering Mode<\/b> <i>Multi-segment<\/i> &middot; <b>ISO Equivalent<\/b> <i>200<\/i> &middot; <b>Exposure Time<\/b> <i>1\/160s<\/i> &middot; <b>Aperture<\/b> <i>ƒ\/3.5<\/i> &middot; <b>Exposure bias<\/b> <i>0 EV<\/i> &middot; <b>Exposure Program<\/b> <i>Manual control<\/i> &middot; <b>White balance<\/b> <i>Manual white balance<\/i> &middot; <b>Flash<\/b> <i>Flash did not fire<\/i> &middot; <b>Resolution<\/b> <i>4896 x 3672<\/i>","dates":{"added":1594237350,"dateTaken":1594032834},"fileDate":"2020-07-06T13:53:54.0Z","path":"DSC09064.webp","imageCaption":"<div class=\"title\">DSC09064<\/div>","fileSize":7716078,"name":"DSC09064.webp","comment":"                               ","location":"58.384363,26.720600","category":"image","camera":{"aperture":3.5,"exposureTime":"1\/160s","originalDate":"2020-07-06T13:53:54.0Z","cameraModel":"DSC-HX90V","location":{"altitude":"37.9 metres","latitude":"58° 23' 3.71\"","lat":58.38436,"long":26.7206,"longitude":"26° 43' 14.16\""},"focalLength35mm":"24mm","resolution":"4896 x 3672","cameraMake":"SONY","isoEquivalent":200,"flash":"Flash did not fire","focalLength":"4mm"}},{"image":{"path":"slides\/DSC09065.webp","width":1500,"height":2000},"thumb":{"path":"thumbs\/DSC09065.webp","width":512,"height":410},"thumbCaption":"<span class=\"nr\">7<\/span><div class=\"title\">DSC09065<\/div>","photodata":"<b>Original Date<\/b> <i>7\/6\/20, 1:53\u202FPM<\/i> &middot; <b>Make<\/b> <i>SONY<\/i> &middot; <b>Camera<\/b> <i>DSC-HX90V<\/i> &middot; <b>Lens<\/b> <i>4.1-123mm f\/3.5-6.4<\/i> &middot; <b>Focal Length (35mm)<\/b> <i>24mm<\/i> &middot; <b>Metering Mode<\/b> <i>Multi-segment<\/i> &middot; <b>ISO Equivalent<\/b> <i>200<\/i> &middot; <b>Exposure Time<\/b> <i>1\/160s<\/i> &middot; <b>Aperture<\/b> <i>ƒ\/3.5<\/i> &middot; <b>Exposure bias<\/b> <i>0 EV<\/i> &middot; <b>Exposure Program<\/b> <i>Manual control<\/i> &middot; <b>White balance<\/b> <i>Manual white balance<\/i> &middot; <b>Flash<\/b> <i>Flash did not fire<\/i> &middot; <b>Resolution<\/b> <i>4896 x 3672<\/i>","dates":{"added":1594237350,"dateTaken":1594032839},"fileDate":"2020-07-06T13:53:58.0Z","path":"DSC09065.webp","imageCaption":"<div class=\"title\">DSC09065<\/div>","fileSize":7642687,"name":"DSC09065.webp","comment":"                               ","location":"58.384343,26.720571","category":"image","camera":{"aperture":3.5,"exposureTime":"1\/160s","originalDate":"2020-07-06T13:53:59.0Z","cameraModel":"DSC-HX90V","location":{"altitude":"38.3 metres","latitude":"58° 23' 3.63\"","lat":58.384342,"long":26.720572,"longitude":"26° 43' 14.06\""},"focalLength35mm":"24mm","resolution":"4896 x 3672","cameraMake":"SONY","isoEquivalent":200,"flash":"Flash did not fire","focalLength":"4mm"}},{"image":{"path":"slides\/DSC09066.webp","width":1500,"height":2000},"thumb":{"path":"thumbs\/DSC09066.webp","width":512,"height":410},"thumbCaption":"<span class=\"nr\">8<\/span><div class=\"title\">DSC09066<\/div>","photodata":"<b>Original Date<\/b> <i>7\/6\/20, 1:54\u202FPM<\/i> &middot; <b>Make<\/b> <i>SONY<\/i> &middot; <b>Camera<\/b> <i>DSC-HX90V<\/i> &middot; <b>Lens<\/b> <i>4.1-123mm f\/3.5-6.4<\/i> &middot; <b>Focal Length (35mm)<\/b> <i>24mm<\/i> &middot; <b>Metering Mode<\/b> <i>Multi-segment<\/i> &middot; <b>ISO Equivalent<\/b> <i>200<\/i> &middot; <b>Exposure Time<\/b> <i>1\/160s<\/i> &middot; <b>Aperture<\/b> <i>ƒ\/3.5<\/i> &middot; <b>Exposure bias<\/b> <i>0 EV<\/i> &middot; <b>Exposure Program<\/b> <i>Manual control<\/i> &middot; <b>White balance<\/b> <i>Manual white balance<\/i> &middot; <b>Flash<\/b> <i>Flash did not fire<\/i> &middot; <b>Resolution<\/b> <i>4896 x 3672<\/i>","dates":{"added":1594237350,"dateTaken":1594032842},"fileDate":"2020-07-06T13:54:02.0Z","path":"DSC09066.webp","imageCaption":"<div class=\"title\">DSC09066<\/div>","fileSize":7164843,"name":"DSC09066.webp","comment":"                               ","location":"58.384345,26.720583","category":"image","camera":{"aperture":3.5,"exposureTime":"1\/160s","originalDate":"2020-07-06T13:54:02.0Z","cameraModel":"DSC-HX90V","location":{"altitude":"38.5 metres","latitude":"58° 23' 3.64\"","lat":58.384346,"long":26.720583,"longitude":"26° 43' 14.1\""},"focalLength35mm":"24mm","resolution":"4896 x 3672","cameraMake":"SONY","isoEquivalent":200,"flash":"Flash did not fire","focalLength":"4mm"}},{"image":{"path":"slides\/DSC09067.webp","width":1500,"height":2000},"thumb":{"path":"thumbs\/DSC09067.webp","width":512,"height":410},"thumbCaption":"<span class=\"nr\">9<\/span><div class=\"title\">DSC09067<\/div>","photodata":"<b>Original Date<\/b> <i>7\/6\/20, 1:54\u202FPM<\/i> &middot; <b>Make<\/b> <i>SONY<\/i> &middot; <b>Camera<\/b> <i>DSC-HX90V<\/i> &middot; <b>Lens<\/b> <i>4.1-123mm f\/3.5-6.4<\/i> &middot; <b>Focal Length (35mm)<\/b> <i>24mm<\/i> &middot; <b>Metering Mode<\/b> <i>Multi-segment<\/i> &middot; <b>ISO Equivalent<\/b> <i>200<\/i> &middot; <b>Exposure Time<\/b> <i>1\/320s<\/i> &middot; <b>Aperture<\/b> <i>ƒ\/3.5<\/i> &middot; <b>Exposure bias<\/b> <i>0 EV<\/i> &middot; <b>Exposure Program<\/b> <i>Manual control<\/i> &middot; <b>White balance<\/b> <i>Manual white balance<\/i> &middot; <b>Flash<\/b> <i>Flash did not fire<\/i> &middot; <b>Resolution<\/b> <i>4896 x 3672<\/i>","dates":{"added":1594237350,"dateTaken":1594032850},"fileDate":"2020-07-06T13:54:10.0Z","path":"DSC09067.webp","imageCaption":"<div class=\"title\">DSC09067<\/div>","fileSize":6833208,"name":"DSC09067.webp","comment":"                               ","location":"58.384286,26.720485","category":"image","camera":{"aperture":3.5,"exposureTime":"1\/320s","originalDate":"2020-07-06T13:54:10.0Z","cameraModel":"DSC-HX90V","location":{"altitude":"39.4 metres","latitude":"58° 23' 3.43\"","lat":58.384285,"long":26.720486,"longitude":"26° 43' 13.75\""},"focalLength35mm":"24mm","resolution":"4896 x 3672","cameraMake":"SONY","isoEquivalent":200,"flash":"Flash did not fire","focalLength":"4mm"}},{"image":{"path":"slides\/DSC09068.webp","width":1500,"height":2000},"thumb":{"path":"thumbs\/DSC09068.webp","width":512,"height":410},"thumbCaption":"<span class=\"nr\">10<\/span><div class=\"title\">DSC09068<\/div>","photodata":"<b>Original Date<\/b> <i>7\/6\/20, 1:54\u202FPM<\/i> &middot; <b>Make<\/b> <i>SONY<\/i> &middot; <b>Camera<\/b> <i>DSC-HX90V<\/i> &middot; <b>Lens<\/b> <i>4.1-123mm f\/3.5-6.4<\/i> &middot; <b>Focal Length (35mm)<\/b> <i>24mm<\/i> &middot; <b>Metering Mode<\/b> <i>Multi-segment<\/i> &middot; <b>ISO Equivalent<\/b> <i>200<\/i> &middot; <b>Exposure Time<\/b> <i>1\/320s<\/i> &middot; <b>Aperture<\/b> <i>ƒ\/3.5<\/i> &middot; <b>Exposure bias<\/b> <i>0 EV<\/i> &middot; <b>Exposure Program<\/b> <i>Manual control<\/i> &middot; <b>White balance<\/b> <i>Manual white balance<\/i> &middot; <b>Flash<\/b> <i>Flash did not fire<\/i> &middot; <b>Resolution<\/b> <i>4896 x 3672<\/i>","dates":{"added":1594237350,"dateTaken":1594032853},"fileDate":"2020-07-06T13:54:12.0Z","path":"DSC09068.webp","imageCaption":"<div class=\"title\">DSC09068<\/div>","fileSize":6916721,"name":"DSC09068.webp","comment":"                               ","location":"58.384275,26.720410","category":"image","camera":{"aperture":3.5,"exposureTime":"1\/320s","originalDate":"2020-07-06T13:54:13.0Z","cameraModel":"DSC-HX90V","location":{"altitude":"40.2 metres","latitude":"58° 23' 3.39\"","lat":58.384274,"long":26.72041,"longitude":"26° 43' 13.48\""},"focalLength35mm":"24mm","resolution":"4896 x 3672","cameraMake":"SONY","isoEquivalent":200,"flash":"Flash did not fire","focalLength":"4mm"}},{"image":{"path":"slides\/DSC09069.webp","width":1500,"height":2000},"thumb":{"path":"thumbs\/DSC09069.webp","width":512,"height":410},"thumbCaption":"<span class=\"nr\">11<\/span><div class=\"title\">DSC09069<\/div>","photodata":"<b>Original Date<\/b> <i>7\/6\/20, 1:54\u202FPM<\/i> &middot; <b>Make<\/b> <i>SONY<\/i> &middot; <b>Camera<\/b> <i>DSC-HX90V<\/i> &middot; <b>Lens<\/b> <i>4.1-123mm f\/3.5-6.4<\/i> &middot; <b>Focal Length (35mm)<\/b> <i>24mm<\/i> &middot; <b>Metering Mode<\/b> <i>Multi-segment<\/i> &middot; <b>ISO Equivalent<\/b> <i>200<\/i> &middot; <b>Exposure Time<\/b> <i>1\/320s<\/i> &middot; <b>Aperture<\/b> <i>ƒ\/3.5<\/i> &middot; <b>Exposure bias<\/b> <i>0 EV<\/i> &middot; <b>Exposure Program<\/b> <i>Manual control<\/i> &middot; <b>White balance<\/b> <i>Manual white balance<\/i> &middot; <b>Flash<\/b> <i>Flash did not fire<\/i> &middot; <b>Resolution<\/b> <i>4896 x 3672<\/i>","dates":{"added":1594237350,"dateTaken":1594032856},"fileDate":"2020-07-06T13:54:16.0Z","path":"DSC09069.webp","imageCaption":"<div class=\"title\">DSC09069<\/div>","fileSize":6896187,"name":"DSC09069.webp","comment":"                               ","location":"58.384273,26.720363","category":"image","camera":{"aperture":3.5,"exposureTime":"1\/320s","originalDate":"2020-07-06T13:54:16.0Z","cameraModel":"DSC-HX90V","location":{"altitude":"40.6 metres","latitude":"58° 23' 3.38\"","lat":58.384274,"long":26.720364,"longitude":"26° 43' 13.31\""},"focalLength35mm":"24mm","resolution":"4896 x 3672","cameraMake":"SONY","isoEquivalent":200,"flash":"Flash did not fire","focalLength":"4mm"}},{"image":{"path":"slides\/DSC09070.webp","width":1500,"height":2000},"thumb":{"path":"thumbs\/DSC09070.webp","width":512,"height":410},"thumbCaption":"<span class=\"nr\">12<\/span><div class=\"title\">DSC09070<\/div>","photodata":"<b>Original Date<\/b> <i>7\/6\/20, 1:54\u202FPM<\/i> &middot; <b>Make<\/b> <i>SONY<\/i> &middot; <b>Camera<\/b> <i>DSC-HX90V<\/i> &middot; <b>Lens<\/b> <i>4.1-123mm f\/3.5-6.4<\/i> &middot; <b>Focal Length (35mm)<\/b> <i>24mm<\/i> &middot; <b>Metering Mode<\/b> <i>Multi-segment<\/i> &middot; <b>ISO Equivalent<\/b> <i>200<\/i> &middot; <b>Exposure Time<\/b> <i>1\/320s<\/i> &middot; <b>Aperture<\/b> <i>ƒ\/3.5<\/i> &middot; <b>Exposure bias<\/b> <i>0 EV<\/i> &middot; <b>Exposure Program<\/b> <i>Manual control<\/i> &middot; <b>White balance<\/b> <i>Manual white balance<\/i> &middot; <b>Flash<\/b> <i>Flash did not fire<\/i> &middot; <b>Resolution<\/b> <i>4896 x 3672<\/i>","dates":{"added":1594237350,"dateTaken":1594032857},"fileDate":"2020-07-06T13:54:16.0Z","path":"DSC09070.webp","imageCaption":"<div class=\"title\">DSC09070<\/div>","fileSize":6714451,"name":"DSC09070.webp","comment":"                               ","location":"58.384265,26.720346","category":"image","camera":{"aperture":3.5,"exposureTime":"1\/320s","originalDate":"2020-07-06T13:54:17.0Z","cameraModel":"DSC-HX90V","location":{"altitude":"41.1 metres","latitude":"58° 23' 3.35\"","lat":58.384266,"long":26.720346,"longitude":"26° 43' 13.25\""},"focalLength35mm":"24mm","resolution":"4896 x 3672","cameraMake":"SONY","isoEquivalent":200,"flash":"Flash did not fire","focalLength":"4mm"}},{"image":{"path":"slides\/DSC09071.webp","width":1500,"height":2000},"thumb":{"path":"thumbs\/DSC09071.webp","width":512,"height":410},"thumbCaption":"<span class=\"nr\">13<\/span><div class=\"title\">DSC09071<\/div>","photodata":"<b>Original Date<\/b> <i>7\/6\/20, 1:54\u202FPM<\/i> &middot; <b>Make<\/b> <i>SONY<\/i> &middot; <b>Camera<\/b> <i>DSC-HX90V<\/i> &middot; <b>Lens<\/b> <i>4.1-123mm f\/3.5-6.4<\/i> &middot; <b>Focal Length (35mm)<\/b> <i>24mm<\/i> &middot; <b>Metering Mode<\/b> <i>Multi-segment<\/i> &middot; <b>ISO Equivalent<\/b> <i>200<\/i> &middot; <b>Exposure Time<\/b> <i>1\/320s<\/i> &middot; <b>Aperture<\/b> <i>ƒ\/3.5<\/i> &middot; <b>Exposure bias<\/b> <i>0 EV<\/i> &middot; <b>Exposure Program<\/b> <i>Manual control<\/i> &middot; <b>White balance<\/b> <i>Manual white balance<\/i> &middot; <b>Flash<\/b> <i>Flash did not fire<\/i> &middot; <b>Resolution<\/b> <i>4896 x 3672<\/i>","dates":{"added":1594237350,"dateTaken":1594032859},"fileDate":"2020-07-06T13:54:18.0Z","path":"DSC09071.webp","imageCaption":"<div class=\"title\">DSC09071<\/div>","fileSize":6806271,"name":"DSC09071.webp","comment":"                               ","location":"58.384258,26.720331","category":"image","camera":{"aperture":3.5,"exposureTime":"1\/320s","originalDate":"2020-07-06T13:54:19.0Z","cameraModel":"DSC-HX90V","location":{"altitude":"41.4 metres","latitude":"58° 23' 3.33\"","lat":58.38426,"long":26.720331,"longitude":"26° 43' 13.19\""},"focalLength35mm":"24mm","resolution":"4896 x 3672","cameraMake":"SONY","isoEquivalent":200,"flash":"Flash did not fire","focalLength":"4mm"}}],"name":"Морина длиннолистная - Morina longifolia","dates":{"added":1658856647,"dateRange":{"0":1594032813,"1":1658740166}},"fileDate":"2023-01-20T18:14:01.557Z"}