{"path":"%D0%9A%D0%BB%D0%B5%D0%BA%D0%B0%D1%87%D0%BA%D0%B0%20%D0%BF%D0%B5%D1%80%D0%B8%D1%81%D1%82%D0%B0%D1%8F%20-%20Staphylea%20pinnata","deepCounters":{"total":35,"images":35,"files":35},"counters":{"total":35,"images":35,"files":35},"thumb":{"path":"thumbs\/SET08608.webp","width":512,"height":410},"thumbCaption":"<h3>Клекачка перистая - Staphylea pinnata<\/h3>","album":{"description":"<br\/>\nHerbarium.INFO Herbarium Photo Collection: Ferns, Conifers, Cycads, Flowers, Trees, Mosses, Grasses, Pests and Diseases.<br\/>\n<br\/><i><b>3221<\/b> species in <b>221<\/b> families and in <b>66<\/b> orders photographed.<br\/>\n<br\/><b>39191<\/b> images total.<\/i><br\/><br\/>\nTry also other sites: <br\/>\n    <a href=\"https:\/\/herbariuminfo.netlify.app\">Herbarium.INFO<\/a>&nbsp;\u2022&nbsp;\n     <a href=\"https:\/\/plantariuminfo.netlify.app\">Plantarium.INFO<\/a>&nbsp;\u2022&nbsp;\n    <a href=\"https:\/\/fungarium.netlify.app\">Fungarium.INFO<\/a>&nbsp;\u2022&nbsp;\n    <a href=\"https:\/\/lichenarium.netlify.app\">Lichenarium.INFO<\/a>&nbsp;\u2022&nbsp;\n    <a href=\"https:\/\/algaerium.netlify.app\">Algaerium.INFO<\/a>","title":"Herbarium.INFO Herbs: Dicotyledones & Monocotyledones"},"objects":[{"image":{"path":"slides\/DSC02976.webp","width":1500,"height":2000},"thumb":{"path":"thumbs\/DSC02976.webp","width":512,"height":410},"thumbCaption":"<span class=\"nr\">1<\/span><div class=\"title\">DSC02976<\/div>","photodata":"<b>Original Date<\/b> <i>5\/24\/15, 1:16\u202FPM<\/i> &middot; <b>Make<\/b> <i>SONY<\/i> &middot; <b>Camera<\/b> <i>DSC-HX50<\/i> &middot; <b>Lens<\/b> <i>4.3-129mm f\/3.5-6.3<\/i> &middot; <b>Focal Length<\/b> <i>4.4 mm<\/i> &middot; <b>Metering Mode<\/b> <i>Multi-segment<\/i> &middot; <b>ISO Equivalent<\/b> <i>80<\/i> &middot; <b>Exposure Time<\/b> <i>1\/640s<\/i> &middot; <b>Aperture<\/b> <i>ƒ\/3.5<\/i> &middot; <b>Exposure bias<\/b> <i>0 EV<\/i> &middot; <b>Exposure Program<\/b> <i>Program normal<\/i> &middot; <b>White balance<\/b> <i>Auto white balance<\/i> &middot; <b>Flash<\/b> <i>Flash did not fire<\/i> &middot; <b>Resolution<\/b> <i>3888 x 5184<\/i>","dates":{"added":1432500352,"dateTaken":1432462608},"fileDate":"2015-05-24T21:17:02.0Z","path":"DSC02976.webp","imageCaption":"<div class=\"title\">DSC02976<\/div>","fileSize":2189880,"name":"DSC02976.webp","comment":"                               ","category":"image","camera":{"aperture":3.5,"exposureTime":"1\/640s","originalDate":"2015-05-24T13:16:48.0Z","cameraModel":"DSC-HX50","resolution":"3888 x 5184","cameraMake":"SONY","isoEquivalent":80,"flash":"Flash did not fire","focalLength":"4mm"}},{"image":{"path":"slides\/DSC02977.webp","width":1500,"height":2000},"thumb":{"path":"thumbs\/DSC02977.webp","width":512,"height":410},"thumbCaption":"<span class=\"nr\">2<\/span><div class=\"title\">DSC02977<\/div>","photodata":"<b>Original Date<\/b> <i>5\/24\/15, 1:16\u202FPM<\/i> &middot; <b>Make<\/b> <i>SONY<\/i> &middot; <b>Camera<\/b> <i>DSC-HX50<\/i> &middot; <b>Lens<\/b> <i>4.3-129mm f\/3.5-6.3<\/i> &middot; <b>Focal Length<\/b> <i>4.4 mm<\/i> &middot; <b>Metering Mode<\/b> <i>Multi-segment<\/i> &middot; <b>ISO Equivalent<\/b> <i>80<\/i> &middot; <b>Exposure Time<\/b> <i>1\/640s<\/i> &middot; <b>Aperture<\/b> <i>ƒ\/3.5<\/i> &middot; <b>Exposure bias<\/b> <i>0 EV<\/i> &middot; <b>Exposure Program<\/b> <i>Program normal<\/i> &middot; <b>White balance<\/b> <i>Auto white balance<\/i> &middot; <b>Flash<\/b> <i>Flash did not fire<\/i> &middot; <b>Resolution<\/b> <i>3888 x 5184<\/i>","dates":{"added":1432500352,"dateTaken":1432462612},"fileDate":"2015-05-24T21:17:04.0Z","path":"DSC02977.webp","imageCaption":"<div class=\"title\">DSC02977<\/div>","fileSize":2059784,"name":"DSC02977.webp","comment":"                               ","category":"image","camera":{"aperture":3.5,"exposureTime":"1\/640s","originalDate":"2015-05-24T13:16:52.0Z","cameraModel":"DSC-HX50","resolution":"3888 x 5184","cameraMake":"SONY","isoEquivalent":80,"flash":"Flash did not fire","focalLength":"4mm"}},{"image":{"path":"slides\/DSC02978.webp","width":1500,"height":2000},"thumb":{"path":"thumbs\/DSC02978.webp","width":512,"height":410},"thumbCaption":"<span class=\"nr\">3<\/span><div class=\"title\">DSC02978<\/div>","photodata":"<b>Original Date<\/b> <i>5\/24\/15, 1:16\u202FPM<\/i> &middot; <b>Make<\/b> <i>SONY<\/i> &middot; <b>Camera<\/b> <i>DSC-HX50<\/i> &middot; <b>Lens<\/b> <i>4.3-129mm f\/3.5-6.3<\/i> &middot; <b>Focal Length<\/b> <i>4.4 mm<\/i> &middot; <b>Metering Mode<\/b> <i>Multi-segment<\/i> &middot; <b>ISO Equivalent<\/b> <i>80<\/i> &middot; <b>Exposure Time<\/b> <i>1\/500s<\/i> &middot; <b>Aperture<\/b> <i>ƒ\/3.5<\/i> &middot; <b>Exposure bias<\/b> <i>0 EV<\/i> &middot; <b>Exposure Program<\/b> <i>Program normal<\/i> &middot; <b>White balance<\/b> <i>Auto white balance<\/i> &middot; <b>Flash<\/b> <i>Flash did not fire<\/i> &middot; <b>Resolution<\/b> <i>3888 x 5184<\/i>","dates":{"added":1432500352,"dateTaken":1432462615},"fileDate":"2015-05-24T21:17:04.0Z","path":"DSC02978.webp","imageCaption":"<div class=\"title\">DSC02978<\/div>","fileSize":4512996,"name":"DSC02978.webp","comment":"                               ","category":"image","camera":{"aperture":3.5,"exposureTime":"1\/500s","originalDate":"2015-05-24T13:16:55.0Z","cameraModel":"DSC-HX50","resolution":"3888 x 5184","cameraMake":"SONY","isoEquivalent":80,"flash":"Flash did not fire","focalLength":"4mm"}},{"image":{"path":"slides\/DSC02979.webp","width":1500,"height":2000},"thumb":{"path":"thumbs\/DSC02979.webp","width":512,"height":410},"thumbCaption":"<span class=\"nr\">4<\/span><div class=\"title\">DSC02979<\/div>","photodata":"<b>Original Date<\/b> <i>5\/24\/15, 1:17\u202FPM<\/i> &middot; <b>Make<\/b> <i>SONY<\/i> &middot; <b>Camera<\/b> <i>DSC-HX50<\/i> &middot; <b>Lens<\/b> <i>4.3-129mm f\/3.5-6.3<\/i> &middot; <b>Focal Length<\/b> <i>4.4 mm<\/i> &middot; <b>Metering Mode<\/b> <i>Multi-segment<\/i> &middot; <b>ISO Equivalent<\/b> <i>80<\/i> &middot; <b>Exposure Time<\/b> <i>1\/640s<\/i> &middot; <b>Aperture<\/b> <i>ƒ\/3.5<\/i> &middot; <b>Exposure bias<\/b> <i>0 EV<\/i> &middot; <b>Exposure Program<\/b> <i>Landscape mode<\/i> &middot; <b>White balance<\/b> <i>Auto white balance<\/i> &middot; <b>Flash<\/b> <i>Flash did not fire<\/i> &middot; <b>Resolution<\/b> <i>3888 x 5184<\/i>","dates":{"added":1432500352,"dateTaken":1432462623},"fileDate":"2015-05-24T21:17:04.0Z","path":"DSC02979.webp","imageCaption":"<div class=\"title\">DSC02979<\/div>","fileSize":5443440,"name":"DSC02979.webp","comment":"                               ","category":"image","camera":{"aperture":3.5,"exposureTime":"1\/640s","originalDate":"2015-05-24T13:17:03.0Z","cameraModel":"DSC-HX50","resolution":"3888 x 5184","cameraMake":"SONY","isoEquivalent":80,"flash":"Flash did not fire","focalLength":"4mm"}},{"image":{"path":"slides\/DSC02980.webp","width":1500,"height":2000},"thumb":{"path":"thumbs\/DSC02980.webp","width":512,"height":410},"thumbCaption":"<span class=\"nr\">5<\/span><div class=\"title\">DSC02980<\/div>","photodata":"<b>Original Date<\/b> <i>5\/24\/15, 1:17\u202FPM<\/i> &middot; <b>Make<\/b> <i>SONY<\/i> &middot; <b>Camera<\/b> <i>DSC-HX50<\/i> &middot; <b>Lens<\/b> <i>4.3-129mm f\/3.5-6.3<\/i> &middot; <b>Focal Length<\/b> <i>4.4 mm<\/i> &middot; <b>Metering Mode<\/b> <i>Multi-segment<\/i> &middot; <b>ISO Equivalent<\/b> <i>80<\/i> &middot; <b>Exposure Time<\/b> <i>1\/800s<\/i> &middot; <b>Aperture<\/b> <i>ƒ\/3.5<\/i> &middot; <b>Exposure bias<\/b> <i>0 EV<\/i> &middot; <b>Exposure Program<\/b> <i>Landscape mode<\/i> &middot; <b>White balance<\/b> <i>Auto white balance<\/i> &middot; <b>Flash<\/b> <i>Flash did not fire<\/i> &middot; <b>Resolution<\/b> <i>3888 x 5184<\/i>","dates":{"added":1432500352,"dateTaken":1432462627},"fileDate":"2015-05-24T21:17:04.0Z","path":"DSC02980.webp","imageCaption":"<div class=\"title\">DSC02980<\/div>","fileSize":3881159,"name":"DSC02980.webp","comment":"                               ","category":"image","camera":{"aperture":3.5,"exposureTime":"1\/800s","originalDate":"2015-05-24T13:17:07.0Z","cameraModel":"DSC-HX50","resolution":"3888 x 5184","cameraMake":"SONY","isoEquivalent":80,"flash":"Flash did not fire","focalLength":"4mm"}},{"image":{"path":"slides\/DSC02981.webp","width":1500,"height":2000},"thumb":{"path":"thumbs\/DSC02981.webp","width":512,"height":410},"thumbCaption":"<span class=\"nr\">6<\/span><div class=\"title\">DSC02981<\/div>","photodata":"<b>Original Date<\/b> <i>5\/24\/15, 1:17\u202FPM<\/i> &middot; <b>Make<\/b> <i>SONY<\/i> &middot; <b>Camera<\/b> <i>DSC-HX50<\/i> &middot; <b>Lens<\/b> <i>4.3-129mm f\/3.5-6.3<\/i> &middot; <b>Focal Length<\/b> <i>4.4 mm<\/i> &middot; <b>Metering Mode<\/b> <i>Multi-segment<\/i> &middot; <b>ISO Equivalent<\/b> <i>80<\/i> &middot; <b>Exposure Time<\/b> <i>1\/800s<\/i> &middot; <b>Aperture<\/b> <i>ƒ\/3.5<\/i> &middot; <b>Exposure bias<\/b> <i>0 EV<\/i> &middot; <b>Exposure Program<\/b> <i>Program normal<\/i> &middot; <b>White balance<\/b> <i>Auto white balance<\/i> &middot; <b>Flash<\/b> <i>Flash did not fire<\/i> &middot; <b>Resolution<\/b> <i>3888 x 5184<\/i>","dates":{"added":1432500352,"dateTaken":1432462638},"fileDate":"2015-05-24T21:17:06.0Z","path":"DSC02981.webp","imageCaption":"<div class=\"title\">DSC02981<\/div>","fileSize":2757697,"name":"DSC02981.webp","comment":"                               ","category":"image","camera":{"aperture":3.5,"exposureTime":"1\/800s","originalDate":"2015-05-24T13:17:18.0Z","cameraModel":"DSC-HX50","resolution":"3888 x 5184","cameraMake":"SONY","isoEquivalent":80,"flash":"Flash did not fire","focalLength":"4mm"}},{"image":{"path":"slides\/DSC04294.webp","width":2000,"height":1500},"thumb":{"path":"thumbs\/DSC04294.webp","width":512,"height":410},"thumbCaption":"<span class=\"nr\">7<\/span><div class=\"title\">DSC04294<\/div>","photodata":"<b>Original Date<\/b> <i>6\/26\/21, 3:16\u202FPM<\/i> &middot; <b>Make<\/b> <i>SONY<\/i> &middot; <b>Camera<\/b> <i>DSC-HX90V<\/i> &middot; <b>Lens<\/b> <i>4.1-123mm f\/3.5-6.4<\/i> &middot; <b>Focal Length (35mm)<\/b> <i>24mm<\/i> &middot; <b>Metering Mode<\/b> <i>Spot<\/i> &middot; <b>ISO Equivalent<\/b> <i>200<\/i> &middot; <b>Exposure Time<\/b> <i>1\/250s<\/i> &middot; <b>Aperture<\/b> <i>ƒ\/3.5<\/i> &middot; <b>Exposure bias<\/b> <i>0 EV<\/i> &middot; <b>Exposure Program<\/b> <i>Manual control<\/i> &middot; <b>White balance<\/b> <i>Manual white balance<\/i> &middot; <b>Flash<\/b> <i>Flash did not fire<\/i> &middot; <b>Resolution<\/b> <i>4896 x 3672<\/i>","dates":{"added":1625163623,"dateTaken":1624709800},"fileDate":"2021-06-26T15:16:40.0Z","path":"DSC04294.webp","imageCaption":"<div class=\"title\">DSC04294<\/div>","fileSize":7212905,"name":"DSC04294.webp","comment":"                               ","location":"59.466575,24.879200","category":"image","camera":{"aperture":3.5,"exposureTime":"1\/250s","originalDate":"2021-06-26T15:16:40.0Z","cameraModel":"DSC-HX90V","location":{"altitude":"15.2 metres","latitude":"59° 27' 59.67\"","lat":59.466576,"long":24.8792,"longitude":"24° 52' 45.12\""},"focalLength35mm":"24mm","resolution":"4896 x 3672","cameraMake":"SONY","isoEquivalent":200,"flash":"Flash did not fire","focalLength":"4mm"}},{"image":{"path":"slides\/DSC04295.webp","width":2000,"height":1500},"thumb":{"path":"thumbs\/DSC04295.webp","width":512,"height":410},"thumbCaption":"<span class=\"nr\">8<\/span><div class=\"title\">DSC04295<\/div>","photodata":"<b>Original Date<\/b> <i>6\/26\/21, 3:16\u202FPM<\/i> &middot; <b>Make<\/b> <i>SONY<\/i> &middot; <b>Camera<\/b> <i>DSC-HX90V<\/i> &middot; <b>Lens<\/b> <i>4.1-123mm f\/3.5-6.4<\/i> &middot; <b>Focal Length (35mm)<\/b> <i>24mm<\/i> &middot; <b>Metering Mode<\/b> <i>Spot<\/i> &middot; <b>ISO Equivalent<\/b> <i>200<\/i> &middot; <b>Exposure Time<\/b> <i>1\/160s<\/i> &middot; <b>Aperture<\/b> <i>ƒ\/3.5<\/i> &middot; <b>Exposure bias<\/b> <i>0 EV<\/i> &middot; <b>Exposure Program<\/b> <i>Manual control<\/i> &middot; <b>White balance<\/b> <i>Manual white balance<\/i> &middot; <b>Flash<\/b> <i>Flash did not fire<\/i> &middot; <b>Resolution<\/b> <i>4896 x 3672<\/i>","dates":{"added":1625163623,"dateTaken":1624709814},"fileDate":"2021-06-26T15:16:54.0Z","path":"DSC04295.webp","imageCaption":"<div class=\"title\">DSC04295<\/div>","fileSize":7442350,"name":"DSC04295.webp","comment":"                               ","location":"59.466565,24.879156","category":"image","camera":{"aperture":3.5,"exposureTime":"1\/160s","originalDate":"2021-06-26T15:16:54.0Z","cameraModel":"DSC-HX90V","location":{"altitude":"15.3 metres","latitude":"59° 27' 59.63\"","lat":59.466564,"long":24.879156,"longitude":"24° 52' 44.96\""},"focalLength35mm":"24mm","resolution":"4896 x 3672","cameraMake":"SONY","isoEquivalent":200,"flash":"Flash did not fire","focalLength":"4mm"}},{"image":{"path":"slides\/DSC04296.webp","width":2000,"height":1500},"thumb":{"path":"thumbs\/DSC04296.webp","width":512,"height":410},"thumbCaption":"<span class=\"nr\">9<\/span><div class=\"title\">DSC04296<\/div>","photodata":"<b>Original Date<\/b> <i>6\/26\/21, 3:16\u202FPM<\/i> &middot; <b>Make<\/b> <i>SONY<\/i> &middot; <b>Camera<\/b> <i>DSC-HX90V<\/i> &middot; <b>Lens<\/b> <i>4.1-123mm f\/3.5-6.4<\/i> &middot; <b>Focal Length (35mm)<\/b> <i>24mm<\/i> &middot; <b>Metering Mode<\/b> <i>Spot<\/i> &middot; <b>ISO Equivalent<\/b> <i>200<\/i> &middot; <b>Exposure Time<\/b> <i>1\/160s<\/i> &middot; <b>Aperture<\/b> <i>ƒ\/3.5<\/i> &middot; <b>Exposure bias<\/b> <i>0 EV<\/i> &middot; <b>Exposure Program<\/b> <i>Manual control<\/i> &middot; <b>White balance<\/b> <i>Manual white balance<\/i> &middot; <b>Flash<\/b> <i>Flash did not fire<\/i> &middot; <b>Resolution<\/b> <i>4896 x 3672<\/i>","dates":{"added":1625163623,"dateTaken":1624709817},"fileDate":"2021-06-26T15:16:56.0Z","path":"DSC04296.webp","imageCaption":"<div class=\"title\">DSC04296<\/div>","fileSize":7157955,"name":"DSC04296.webp","comment":"                               ","location":"59.466576,24.879168","category":"image","camera":{"aperture":3.5,"exposureTime":"1\/160s","originalDate":"2021-06-26T15:16:57.0Z","cameraModel":"DSC-HX90V","location":{"altitude":"15.4 metres","latitude":"59° 27' 59.68\"","lat":59.466576,"long":24.879168,"longitude":"24° 52' 45.01\""},"focalLength35mm":"24mm","resolution":"4896 x 3672","cameraMake":"SONY","isoEquivalent":200,"flash":"Flash did not fire","focalLength":"4mm"}},{"image":{"path":"slides\/DSC04297.webp","width":1500,"height":2000},"thumb":{"path":"thumbs\/DSC04297.webp","width":512,"height":410},"thumbCaption":"<span class=\"nr\">10<\/span><div class=\"title\">DSC04297<\/div>","photodata":"<b>Original Date<\/b> <i>6\/26\/21, 3:17\u202FPM<\/i> &middot; <b>Make<\/b> <i>SONY<\/i> &middot; <b>Camera<\/b> <i>DSC-HX90V<\/i> &middot; <b>Lens<\/b> <i>4.1-123mm f\/3.5-6.4<\/i> &middot; <b>Focal Length (35mm)<\/b> <i>24mm<\/i> &middot; <b>Metering Mode<\/b> <i>Spot<\/i> &middot; <b>ISO Equivalent<\/b> <i>200<\/i> &middot; <b>Exposure Time<\/b> <i>1\/200s<\/i> &middot; <b>Aperture<\/b> <i>ƒ\/3.5<\/i> &middot; <b>Exposure bias<\/b> <i>0 EV<\/i> &middot; <b>Exposure Program<\/b> <i>Manual control<\/i> &middot; <b>White balance<\/b> <i>Manual white balance<\/i> &middot; <b>Flash<\/b> <i>Flash did not fire<\/i> &middot; <b>Resolution<\/b> <i>4896 x 3672<\/i>","dates":{"added":1625163623,"dateTaken":1624709825},"fileDate":"2021-06-26T15:17:04.0Z","path":"DSC04297.webp","imageCaption":"<div class=\"title\">DSC04297<\/div>","fileSize":7863473,"name":"DSC04297.webp","comment":"                               ","location":"59.466575,24.879166","category":"image","camera":{"aperture":3.5,"exposureTime":"1\/200s","originalDate":"2021-06-26T15:17:05.0Z","cameraModel":"DSC-HX90V","location":{"altitude":"15.4 metres","latitude":"59° 27' 59.67\"","lat":59.466576,"long":24.879166,"longitude":"24° 52' 45\""},"focalLength35mm":"24mm","resolution":"4896 x 3672","cameraMake":"SONY","isoEquivalent":200,"flash":"Flash did not fire","focalLength":"4mm"}},{"image":{"path":"slides\/DSC04298.webp","width":1500,"height":2000},"thumb":{"path":"thumbs\/DSC04298.webp","width":512,"height":410},"thumbCaption":"<span class=\"nr\">11<\/span><div class=\"title\">DSC04298<\/div>","photodata":"<b>Original Date<\/b> <i>6\/26\/21, 3:17\u202FPM<\/i> &middot; <b>Make<\/b> <i>SONY<\/i> &middot; <b>Camera<\/b> <i>DSC-HX90V<\/i> &middot; <b>Lens<\/b> <i>4.1-123mm f\/3.5-6.4<\/i> &middot; <b>Focal Length (35mm)<\/b> <i>24mm<\/i> &middot; <b>Metering Mode<\/b> <i>Spot<\/i> &middot; <b>ISO Equivalent<\/b> <i>200<\/i> &middot; <b>Exposure Time<\/b> <i>1\/160s<\/i> &middot; <b>Aperture<\/b> <i>ƒ\/3.5<\/i> &middot; <b>Exposure bias<\/b> <i>0 EV<\/i> &middot; <b>Exposure Program<\/b> <i>Manual control<\/i> &middot; <b>White balance<\/b> <i>Manual white balance<\/i> &middot; <b>Flash<\/b> <i>Flash did not fire<\/i> &middot; <b>Resolution<\/b> <i>4896 x 3672<\/i>","dates":{"added":1625163623,"dateTaken":1624709834},"fileDate":"2021-06-26T15:17:14.0Z","path":"DSC04298.webp","imageCaption":"<div class=\"title\">DSC04298<\/div>","fileSize":7239564,"name":"DSC04298.webp","comment":"                               ","location":"59.466581,24.879151","category":"image","camera":{"aperture":3.5,"exposureTime":"1\/160s","originalDate":"2021-06-26T15:17:14.0Z","cameraModel":"DSC-HX90V","location":{"altitude":"15.5 metres","latitude":"59° 27' 59.69\"","lat":59.46658,"long":24.87915,"longitude":"24° 52' 44.95\""},"focalLength35mm":"24mm","resolution":"4896 x 3672","cameraMake":"SONY","isoEquivalent":200,"flash":"Flash did not fire","focalLength":"4mm"}},{"image":{"path":"slides\/DSC04299.webp","width":2000,"height":1500},"thumb":{"path":"thumbs\/DSC04299.webp","width":512,"height":410},"thumbCaption":"<span class=\"nr\">12<\/span><div class=\"title\">DSC04299<\/div>","photodata":"<b>Original Date<\/b> <i>6\/26\/21, 3:17\u202FPM<\/i> &middot; <b>Make<\/b> <i>SONY<\/i> &middot; <b>Camera<\/b> <i>DSC-HX90V<\/i> &middot; <b>Lens<\/b> <i>4.1-123mm f\/3.5-6.4<\/i> &middot; <b>Focal Length (35mm)<\/b> <i>24mm<\/i> &middot; <b>Metering Mode<\/b> <i>Spot<\/i> &middot; <b>ISO Equivalent<\/b> <i>200<\/i> &middot; <b>Exposure Time<\/b> <i>1\/100s<\/i> &middot; <b>Aperture<\/b> <i>ƒ\/3.5<\/i> &middot; <b>Exposure bias<\/b> <i>0 EV<\/i> &middot; <b>Exposure Program<\/b> <i>Manual control<\/i> &middot; <b>White balance<\/b> <i>Manual white balance<\/i> &middot; <b>Flash<\/b> <i>Flash did not fire<\/i> &middot; <b>Resolution<\/b> <i>4896 x 3672<\/i>","dates":{"added":1625163623,"dateTaken":1624709852},"fileDate":"2021-06-26T15:17:32.0Z","path":"DSC04299.webp","imageCaption":"<div class=\"title\">DSC04299<\/div>","fileSize":8359719,"name":"DSC04299.webp","comment":"                               ","location":"59.466648,24.879181","category":"image","camera":{"aperture":3.5,"exposureTime":"1\/100s","originalDate":"2021-06-26T15:17:32.0Z","cameraModel":"DSC-HX90V","location":{"altitude":"15.1 metres","latitude":"59° 27' 59.93\"","lat":59.46665,"long":24.87918,"longitude":"24° 52' 45.05\""},"focalLength35mm":"24mm","resolution":"4896 x 3672","cameraMake":"SONY","isoEquivalent":200,"flash":"Flash did not fire","focalLength":"4mm"}},{"image":{"path":"slides\/DSC04300.webp","width":2000,"height":1500},"thumb":{"path":"thumbs\/DSC04300.webp","width":512,"height":410},"thumbCaption":"<span class=\"nr\">13<\/span><div class=\"title\">DSC04300<\/div>","photodata":"<b>Original Date<\/b> <i>6\/26\/21, 3:17\u202FPM<\/i> &middot; <b>Make<\/b> <i>SONY<\/i> &middot; <b>Camera<\/b> <i>DSC-HX90V<\/i> &middot; <b>Lens<\/b> <i>4.1-123mm f\/3.5-6.4<\/i> &middot; <b>Focal Length (35mm)<\/b> <i>24mm<\/i> &middot; <b>Metering Mode<\/b> <i>Spot<\/i> &middot; <b>ISO Equivalent<\/b> <i>200<\/i> &middot; <b>Exposure Time<\/b> <i>1\/125s<\/i> &middot; <b>Aperture<\/b> <i>ƒ\/3.5<\/i> &middot; <b>Exposure bias<\/b> <i>0 EV<\/i> &middot; <b>Exposure Program<\/b> <i>Manual control<\/i> &middot; <b>White balance<\/b> <i>Manual white balance<\/i> &middot; <b>Flash<\/b> <i>Flash did not fire<\/i> &middot; <b>Resolution<\/b> <i>4896 x 3672<\/i>","dates":{"added":1625163623,"dateTaken":1624709870},"fileDate":"2021-06-26T15:17:50.0Z","path":"DSC04300.webp","imageCaption":"<div class=\"title\">DSC04300<\/div>","fileSize":7713421,"name":"DSC04300.webp","comment":"                               ","location":"59.466610,24.879270","category":"image","camera":{"aperture":3.5,"exposureTime":"1\/125s","originalDate":"2021-06-26T15:17:50.0Z","cameraModel":"DSC-HX90V","location":{"altitude":"14.3 metres","latitude":"59° 27' 59.8\"","lat":59.46661,"long":24.87927,"longitude":"24° 52' 45.37\""},"focalLength35mm":"24mm","resolution":"4896 x 3672","cameraMake":"SONY","isoEquivalent":200,"flash":"Flash did not fire","focalLength":"4mm"}},{"image":{"path":"slides\/DSC04301.webp","width":2000,"height":1500},"thumb":{"path":"thumbs\/DSC04301.webp","width":512,"height":410},"thumbCaption":"<span class=\"nr\">14<\/span><div class=\"title\">DSC04301<\/div>","photodata":"<b>Original Date<\/b> <i>6\/26\/21, 3:18\u202FPM<\/i> &middot; <b>Make<\/b> <i>SONY<\/i> &middot; <b>Camera<\/b> <i>DSC-HX90V<\/i> &middot; <b>Lens<\/b> <i>4.1-123mm f\/3.5-6.4<\/i> &middot; <b>Focal Length (35mm)<\/b> <i>24mm<\/i> &middot; <b>Metering Mode<\/b> <i>Spot<\/i> &middot; <b>ISO Equivalent<\/b> <i>200<\/i> &middot; <b>Exposure Time<\/b> <i>1\/250s<\/i> &middot; <b>Aperture<\/b> <i>ƒ\/3.5<\/i> &middot; <b>Exposure bias<\/b> <i>0 EV<\/i> &middot; <b>Exposure Program<\/b> <i>Manual control<\/i> &middot; <b>White balance<\/b> <i>Manual white balance<\/i> &middot; <b>Flash<\/b> <i>Flash did not fire<\/i> &middot; <b>Resolution<\/b> <i>4896 x 3672<\/i>","dates":{"added":1625163623,"dateTaken":1624709880},"fileDate":"2021-06-26T15:18:00.0Z","path":"DSC04301.webp","imageCaption":"<div class=\"title\">DSC04301<\/div>","fileSize":7346070,"name":"DSC04301.webp","comment":"                               ","location":"59.466585,24.879321","category":"image","camera":{"aperture":3.5,"exposureTime":"1\/250s","originalDate":"2021-06-26T15:18:00.0Z","cameraModel":"DSC-HX90V","location":{"altitude":"14.3 metres","latitude":"59° 27' 59.71\"","lat":59.466583,"long":24.87932,"longitude":"24° 52' 45.56\""},"focalLength35mm":"24mm","resolution":"4896 x 3672","cameraMake":"SONY","isoEquivalent":200,"flash":"Flash did not fire","focalLength":"4mm"}},{"image":{"path":"slides\/DSC04302.webp","width":1500,"height":2000},"thumb":{"path":"thumbs\/DSC04302.webp","width":512,"height":410},"thumbCaption":"<span class=\"nr\">15<\/span><div class=\"title\">DSC04302<\/div>","photodata":"<b>Original Date<\/b> <i>6\/26\/21, 3:18\u202FPM<\/i> &middot; <b>Make<\/b> <i>SONY<\/i> &middot; <b>Camera<\/b> <i>DSC-HX90V<\/i> &middot; <b>Lens<\/b> <i>4.1-123mm f\/3.5-6.4<\/i> &middot; <b>Focal Length (35mm)<\/b> <i>24mm<\/i> &middot; <b>Metering Mode<\/b> <i>Spot<\/i> &middot; <b>ISO Equivalent<\/b> <i>200<\/i> &middot; <b>Exposure Time<\/b> <i>1\/100s<\/i> &middot; <b>Aperture<\/b> <i>ƒ\/3.5<\/i> &middot; <b>Exposure bias<\/b> <i>0 EV<\/i> &middot; <b>Exposure Program<\/b> <i>Manual control<\/i> &middot; <b>White balance<\/b> <i>Manual white balance<\/i> &middot; <b>Flash<\/b> <i>Flash did not fire<\/i> &middot; <b>Resolution<\/b> <i>4896 x 3672<\/i>","dates":{"added":1625163623,"dateTaken":1624709916},"fileDate":"2021-06-26T15:18:36.0Z","path":"DSC04302.webp","imageCaption":"<div class=\"title\">DSC04302<\/div>","fileSize":7784333,"name":"DSC04302.webp","comment":"                               ","location":"59.466595,24.879348","category":"image","camera":{"aperture":3.5,"exposureTime":"1\/100s","originalDate":"2021-06-26T15:18:36.0Z","cameraModel":"DSC-HX90V","location":{"altitude":"13.8 metres","latitude":"59° 27' 59.74\"","lat":59.466595,"long":24.879349,"longitude":"24° 52' 45.65\""},"focalLength35mm":"24mm","resolution":"4896 x 3672","cameraMake":"SONY","isoEquivalent":200,"flash":"Flash did not fire","focalLength":"4mm"}},{"image":{"path":"slides\/DSC04439.webp","width":2000,"height":1500},"thumb":{"path":"thumbs\/DSC04439.webp","width":512,"height":410},"thumbCaption":"<span class=\"nr\">16<\/span><div class=\"title\">DSC04439<\/div>","photodata":"<b>Original Date<\/b> <i>6\/28\/15, 4:10\u202FPM<\/i> &middot; <b>Make<\/b> <i>SONY<\/i> &middot; <b>Camera<\/b> <i>DSC-HX50<\/i> &middot; <b>Lens<\/b> <i>4.3-129mm f\/3.5-6.3<\/i> &middot; <b>Focal Length<\/b> <i>4.8 mm<\/i> &middot; <b>Metering Mode<\/b> <i>Multi-segment<\/i> &middot; <b>ISO Equivalent<\/b> <i>100<\/i> &middot; <b>Exposure Time<\/b> <i>1\/100s<\/i> &middot; <b>Aperture<\/b> <i>ƒ\/3.5<\/i> &middot; <b>Exposure bias<\/b> <i>0 EV<\/i> &middot; <b>Exposure Program<\/b> <i>Landscape mode<\/i> &middot; <b>White balance<\/b> <i>Auto white balance<\/i> &middot; <b>Flash<\/b> <i>Flash did not fire<\/i> &middot; <b>Resolution<\/b> <i>5184 x 3888<\/i>","dates":{"added":1435792270,"dateTaken":1435497047},"fileDate":"2015-06-29T16:52:38.0Z","path":"DSC04439.webp","imageCaption":"<div class=\"title\">DSC04439<\/div>","fileSize":2163529,"name":"DSC04439.webp","comment":"                               ","category":"image","camera":{"aperture":3.5,"exposureTime":"1\/100s","originalDate":"2015-06-28T16:10:47.0Z","cameraModel":"DSC-HX50","resolution":"5184 x 3888","cameraMake":"SONY","isoEquivalent":100,"flash":"Flash did not fire","focalLength":"5mm"}},{"image":{"path":"slides\/DSC04440.webp","width":1500,"height":2000},"thumb":{"path":"thumbs\/DSC04440.webp","width":512,"height":410},"thumbCaption":"<span class=\"nr\">17<\/span><div class=\"title\">DSC04440<\/div>","photodata":"<b>Original Date<\/b> <i>6\/28\/15, 4:10\u202FPM<\/i> &middot; <b>Make<\/b> <i>SONY<\/i> &middot; <b>Camera<\/b> <i>DSC-HX50<\/i> &middot; <b>Lens<\/b> <i>4.3-129mm f\/3.5-6.3<\/i> &middot; <b>Focal Length<\/b> <i>10.7 mm<\/i> &middot; <b>Metering Mode<\/b> <i>Multi-segment<\/i> &middot; <b>ISO Equivalent<\/b> <i>80<\/i> &middot; <b>Exposure Time<\/b> <i>1\/400s<\/i> &middot; <b>Aperture<\/b> <i>ƒ\/5<\/i> &middot; <b>Exposure bias<\/b> <i>0 EV<\/i> &middot; <b>Exposure Program<\/b> <i>Landscape mode<\/i> &middot; <b>White balance<\/b> <i>Auto white balance<\/i> &middot; <b>Flash<\/b> <i>Flash did not fire<\/i> &middot; <b>Resolution<\/b> <i>3888 x 5184<\/i>","dates":{"added":1435792270,"dateTaken":1435497059},"fileDate":"2015-06-29T16:52:38.0Z","path":"DSC04440.webp","imageCaption":"<div class=\"title\">DSC04440<\/div>","fileSize":2419139,"name":"DSC04440.webp","comment":"                               ","category":"image","camera":{"aperture":5.0,"exposureTime":"1\/400s","originalDate":"2015-06-28T16:10:59.0Z","cameraModel":"DSC-HX50","resolution":"3888 x 5184","cameraMake":"SONY","isoEquivalent":80,"flash":"Flash did not fire","focalLength":"11mm"}},{"image":{"path":"slides\/DSC04441.webp","width":2000,"height":1500},"thumb":{"path":"thumbs\/DSC04441.webp","width":512,"height":410},"thumbCaption":"<span class=\"nr\">18<\/span><div class=\"title\">DSC04441<\/div>","photodata":"<b>Original Date<\/b> <i>6\/28\/15, 4:11\u202FPM<\/i> &middot; <b>Make<\/b> <i>SONY<\/i> &middot; <b>Camera<\/b> <i>DSC-HX50<\/i> &middot; <b>Lens<\/b> <i>4.3-129mm f\/3.5-6.3<\/i> &middot; <b>Focal Length<\/b> <i>6.5 mm<\/i> &middot; <b>Metering Mode<\/b> <i>Multi-segment<\/i> &middot; <b>ISO Equivalent<\/b> <i>80<\/i> &middot; <b>Exposure Time<\/b> <i>1\/1000s<\/i> &middot; <b>Aperture<\/b> <i>ƒ\/4<\/i> &middot; <b>Exposure bias<\/b> <i>-0.3 EV<\/i> &middot; <b>Exposure Program<\/b> <i>Program normal<\/i> &middot; <b>White balance<\/b> <i>Auto white balance<\/i> &middot; <b>Flash<\/b> <i>Flash did not fire<\/i> &middot; <b>Resolution<\/b> <i>5184 x 3888<\/i>","dates":{"added":1435792270,"dateTaken":1435497090},"fileDate":"2015-06-29T16:52:40.0Z","path":"DSC04441.webp","imageCaption":"<div class=\"title\">DSC04441<\/div>","fileSize":1570199,"name":"DSC04441.webp","comment":"                               ","category":"image","camera":{"aperture":4.0,"exposureTime":"1\/1000s","originalDate":"2015-06-28T16:11:30.0Z","cameraModel":"DSC-HX50","resolution":"5184 x 3888","cameraMake":"SONY","isoEquivalent":80,"flash":"Flash did not fire","focalLength":"6mm"}},{"path":"DSC04441_.webp","image":{"path":"slides\/DSC04441_.webp","width":1811,"height":1552},"imageCaption":"<div class=\"title\">DSC04441 <\/div>","thumb":{"path":"thumbs\/DSC04441_.webp","width":512,"height":410},"fileSize":288346,"thumbCaption":"<span class=\"nr\">19<\/span><div class=\"title\">DSC04441 <\/div>","name":"DSC04441_.webp","dates":{"added":1435792270,"dateTaken":1435791250},"fileDate":"2015-07-02T01:54:10.0Z","category":"image","camera":{"originalDate":"2015-07-02T01:54:10.0Z"}},{"image":{"path":"slides\/DSC04442.webp","width":2000,"height":1500},"thumb":{"path":"thumbs\/DSC04442.webp","width":512,"height":410},"thumbCaption":"<span class=\"nr\">20<\/span><div class=\"title\">DSC04442<\/div>","photodata":"<b>Original Date<\/b> <i>6\/28\/15, 4:11\u202FPM<\/i> &middot; <b>Make<\/b> <i>SONY<\/i> &middot; <b>Camera<\/b> <i>DSC-HX50<\/i> &middot; <b>Lens<\/b> <i>4.3-129mm f\/3.5-6.3<\/i> &middot; <b>Focal Length<\/b> <i>6.5 mm<\/i> &middot; <b>Metering Mode<\/b> <i>Multi-segment<\/i> &middot; <b>ISO Equivalent<\/b> <i>80<\/i> &middot; <b>Exposure Time<\/b> <i>1\/800s<\/i> &middot; <b>Aperture<\/b> <i>ƒ\/4<\/i> &middot; <b>Exposure bias<\/b> <i>-0.3 EV<\/i> &middot; <b>Exposure Program<\/b> <i>Program normal<\/i> &middot; <b>White balance<\/b> <i>Auto white balance<\/i> &middot; <b>Flash<\/b> <i>Flash did not fire<\/i> &middot; <b>Resolution<\/b> <i>5184 x 3888<\/i>","dates":{"added":1435792270,"dateTaken":1435497095},"fileDate":"2015-06-29T16:52:40.0Z","path":"DSC04442.webp","imageCaption":"<div class=\"title\">DSC04442<\/div>","fileSize":1524446,"name":"DSC04442.webp","comment":"                               ","category":"image","camera":{"aperture":4.0,"exposureTime":"1\/800s","originalDate":"2015-06-28T16:11:35.0Z","cameraModel":"DSC-HX50","resolution":"5184 x 3888","cameraMake":"SONY","isoEquivalent":80,"flash":"Flash did not fire","focalLength":"6mm"}},{"image":{"path":"slides\/DSC04443.webp","width":1500,"height":2000},"thumb":{"path":"thumbs\/DSC04443.webp","width":512,"height":410},"thumbCaption":"<span class=\"nr\">21<\/span><div class=\"title\">DSC04443<\/div>","photodata":"<b>Original Date<\/b> <i>6\/28\/15, 4:11\u202FPM<\/i> &middot; <b>Make<\/b> <i>SONY<\/i> &middot; <b>Camera<\/b> <i>DSC-HX50<\/i> &middot; <b>Lens<\/b> <i>4.3-129mm f\/3.5-6.3<\/i> &middot; <b>Focal Length<\/b> <i>6.5 mm<\/i> &middot; <b>Metering Mode<\/b> <i>Multi-segment<\/i> &middot; <b>ISO Equivalent<\/b> <i>80<\/i> &middot; <b>Exposure Time<\/b> <i>1\/500s<\/i> &middot; <b>Aperture<\/b> <i>ƒ\/4<\/i> &middot; <b>Exposure bias<\/b> <i>0 EV<\/i> &middot; <b>Exposure Program<\/b> <i>Landscape mode<\/i> &middot; <b>White balance<\/b> <i>Auto white balance<\/i> &middot; <b>Flash<\/b> <i>Flash did not fire<\/i> &middot; <b>Resolution<\/b> <i>3888 x 5184<\/i>","dates":{"added":1435792270,"dateTaken":1435497109},"fileDate":"2015-06-29T16:52:42.0Z","path":"DSC04443.webp","imageCaption":"<div class=\"title\">DSC04443<\/div>","fileSize":2739006,"name":"DSC04443.webp","comment":"                               ","category":"image","camera":{"aperture":4.0,"exposureTime":"1\/500s","originalDate":"2015-06-28T16:11:49.0Z","cameraModel":"DSC-HX50","resolution":"3888 x 5184","cameraMake":"SONY","isoEquivalent":80,"flash":"Flash did not fire","focalLength":"6mm"}},{"image":{"path":"slides\/DSC04444.webp","width":2000,"height":1500},"thumb":{"path":"thumbs\/DSC04444.webp","width":512,"height":410},"thumbCaption":"<span class=\"nr\">22<\/span><div class=\"title\">DSC04444<\/div>","photodata":"<b>Original Date<\/b> <i>6\/28\/15, 4:12\u202FPM<\/i> &middot; <b>Make<\/b> <i>SONY<\/i> &middot; <b>Camera<\/b> <i>DSC-HX50<\/i> &middot; <b>Lens<\/b> <i>4.3-129mm f\/3.5-6.3<\/i> &middot; <b>Focal Length<\/b> <i>6.5 mm<\/i> &middot; <b>Metering Mode<\/b> <i>Multi-segment<\/i> &middot; <b>ISO Equivalent<\/b> <i>80<\/i> &middot; <b>Exposure Time<\/b> <i>1\/400s<\/i> &middot; <b>Aperture<\/b> <i>ƒ\/4<\/i> &middot; <b>Exposure bias<\/b> <i>-0.3 EV<\/i> &middot; <b>Exposure Program<\/b> <i>Program normal<\/i> &middot; <b>White balance<\/b> <i>Auto white balance<\/i> &middot; <b>Flash<\/b> <i>Flash did not fire<\/i> &middot; <b>Resolution<\/b> <i>5184 x 3888<\/i>","dates":{"added":1435792270,"dateTaken":1435497132},"fileDate":"2015-06-29T16:52:44.0Z","path":"DSC04444.webp","imageCaption":"<div class=\"title\">DSC04444<\/div>","fileSize":1629974,"name":"DSC04444.webp","comment":"                               ","category":"image","camera":{"aperture":4.0,"exposureTime":"1\/400s","originalDate":"2015-06-28T16:12:12.0Z","cameraModel":"DSC-HX50","resolution":"5184 x 3888","cameraMake":"SONY","isoEquivalent":80,"flash":"Flash did not fire","focalLength":"6mm"}},{"image":{"path":"slides\/DSC04445.webp","width":2000,"height":1500},"thumb":{"path":"thumbs\/DSC04445.webp","width":512,"height":410},"thumbCaption":"<span class=\"nr\">23<\/span><div class=\"title\">DSC04445<\/div>","photodata":"<b>Original Date<\/b> <i>6\/28\/15, 4:12\u202FPM<\/i> &middot; <b>Make<\/b> <i>SONY<\/i> &middot; <b>Camera<\/b> <i>DSC-HX50<\/i> &middot; <b>Lens<\/b> <i>4.3-129mm f\/3.5-6.3<\/i> &middot; <b>Focal Length<\/b> <i>6.5 mm<\/i> &middot; <b>Metering Mode<\/b> <i>Multi-segment<\/i> &middot; <b>ISO Equivalent<\/b> <i>80<\/i> &middot; <b>Exposure Time<\/b> <i>1\/500s<\/i> &middot; <b>Aperture<\/b> <i>ƒ\/4<\/i> &middot; <b>Exposure bias<\/b> <i>-0.3 EV<\/i> &middot; <b>Exposure Program<\/b> <i>Program normal<\/i> &middot; <b>White balance<\/b> <i>Auto white balance<\/i> &middot; <b>Flash<\/b> <i>Flash did not fire<\/i> &middot; <b>Resolution<\/b> <i>5184 x 3888<\/i>","dates":{"added":1435792270,"dateTaken":1435497146},"fileDate":"2015-06-29T16:52:44.0Z","path":"DSC04445.webp","imageCaption":"<div class=\"title\">DSC04445<\/div>","fileSize":1564219,"name":"DSC04445.webp","comment":"                               ","category":"image","camera":{"aperture":4.0,"exposureTime":"1\/500s","originalDate":"2015-06-28T16:12:26.0Z","cameraModel":"DSC-HX50","resolution":"5184 x 3888","cameraMake":"SONY","isoEquivalent":80,"flash":"Flash did not fire","focalLength":"6mm"}},{"image":{"path":"slides\/DSC04446.webp","width":2000,"height":1500},"thumb":{"path":"thumbs\/DSC04446.webp","width":512,"height":410},"thumbCaption":"<span class=\"nr\">24<\/span><div class=\"title\">DSC04446<\/div>","photodata":"<b>Original Date<\/b> <i>6\/28\/15, 4:12\u202FPM<\/i> &middot; <b>Make<\/b> <i>SONY<\/i> &middot; <b>Camera<\/b> <i>DSC-HX50<\/i> &middot; <b>Lens<\/b> <i>4.3-129mm f\/3.5-6.3<\/i> &middot; <b>Focal Length<\/b> <i>9.8 mm<\/i> &middot; <b>Metering Mode<\/b> <i>Multi-segment<\/i> &middot; <b>ISO Equivalent<\/b> <i>80<\/i> &middot; <b>Exposure Time<\/b> <i>1\/400s<\/i> &middot; <b>Aperture<\/b> <i>ƒ\/5<\/i> &middot; <b>Exposure bias<\/b> <i>0 EV<\/i> &middot; <b>Exposure Program<\/b> <i>Landscape mode<\/i> &middot; <b>White balance<\/b> <i>Auto white balance<\/i> &middot; <b>Flash<\/b> <i>Flash did not fire<\/i> &middot; <b>Resolution<\/b> <i>5184 x 3888<\/i>","dates":{"added":1435792270,"dateTaken":1435497166},"fileDate":"2015-06-29T16:52:46.0Z","path":"DSC04446.webp","imageCaption":"<div class=\"title\">DSC04446<\/div>","fileSize":2771209,"name":"DSC04446.webp","comment":"                               ","category":"image","camera":{"aperture":5.0,"exposureTime":"1\/400s","originalDate":"2015-06-28T16:12:46.0Z","cameraModel":"DSC-HX50","resolution":"5184 x 3888","cameraMake":"SONY","isoEquivalent":80,"flash":"Flash did not fire","focalLength":"10mm"}},{"image":{"path":"slides\/DSC04447.webp","width":1500,"height":2000},"thumb":{"path":"thumbs\/DSC04447.webp","width":512,"height":410},"thumbCaption":"<span class=\"nr\">25<\/span><div class=\"title\">DSC04447<\/div>","photodata":"<b>Original Date<\/b> <i>6\/28\/15, 4:12\u202FPM<\/i> &middot; <b>Make<\/b> <i>SONY<\/i> &middot; <b>Camera<\/b> <i>DSC-HX50<\/i> &middot; <b>Lens<\/b> <i>4.3-129mm f\/3.5-6.3<\/i> &middot; <b>Focal Length<\/b> <i>9.8 mm<\/i> &middot; <b>Metering Mode<\/b> <i>Multi-segment<\/i> &middot; <b>ISO Equivalent<\/b> <i>80<\/i> &middot; <b>Exposure Time<\/b> <i>1\/200s<\/i> &middot; <b>Aperture<\/b> <i>ƒ\/5<\/i> &middot; <b>Exposure bias<\/b> <i>0 EV<\/i> &middot; <b>Exposure Program<\/b> <i>Landscape mode<\/i> &middot; <b>White balance<\/b> <i>Auto white balance<\/i> &middot; <b>Flash<\/b> <i>Flash did not fire<\/i> &middot; <b>Resolution<\/b> <i>3888 x 5184<\/i>","dates":{"added":1435792270,"dateTaken":1435497172},"fileDate":"2015-06-29T16:52:46.0Z","path":"DSC04447.webp","imageCaption":"<div class=\"title\">DSC04447<\/div>","fileSize":3305745,"name":"DSC04447.webp","comment":"                               ","category":"image","camera":{"aperture":5.0,"exposureTime":"1\/200s","originalDate":"2015-06-28T16:12:52.0Z","cameraModel":"DSC-HX50","resolution":"3888 x 5184","cameraMake":"SONY","isoEquivalent":80,"flash":"Flash did not fire","focalLength":"10mm"}},{"image":{"path":"slides\/DSC04448.webp","width":1500,"height":2000},"thumb":{"path":"thumbs\/DSC04448.webp","width":512,"height":410},"thumbCaption":"<span class=\"nr\">26<\/span><div class=\"title\">DSC04448<\/div>","photodata":"<b>Original Date<\/b> <i>6\/28\/15, 4:12\u202FPM<\/i> &middot; <b>Make<\/b> <i>SONY<\/i> &middot; <b>Camera<\/b> <i>DSC-HX50<\/i> &middot; <b>Lens<\/b> <i>4.3-129mm f\/3.5-6.3<\/i> &middot; <b>Focal Length<\/b> <i>9.8 mm<\/i> &middot; <b>Metering Mode<\/b> <i>Multi-segment<\/i> &middot; <b>ISO Equivalent<\/b> <i>80<\/i> &middot; <b>Exposure Time<\/b> <i>1\/60s<\/i> &middot; <b>Aperture<\/b> <i>ƒ\/5<\/i> &middot; <b>Exposure bias<\/b> <i>0 EV<\/i> &middot; <b>Exposure Program<\/b> <i>Landscape mode<\/i> &middot; <b>White balance<\/b> <i>Auto white balance<\/i> &middot; <b>Flash<\/b> <i>Flash did not fire<\/i> &middot; <b>Resolution<\/b> <i>3888 x 5184<\/i>","dates":{"added":1435792270,"dateTaken":1435497179},"fileDate":"2015-06-29T16:52:46.0Z","path":"DSC04448.webp","imageCaption":"<div class=\"title\">DSC04448<\/div>","fileSize":2818594,"name":"DSC04448.webp","comment":"                               ","category":"image","camera":{"aperture":5.0,"exposureTime":"1\/60s","originalDate":"2015-06-28T16:12:59.0Z","cameraModel":"DSC-HX50","resolution":"3888 x 5184","cameraMake":"SONY","isoEquivalent":80,"flash":"Flash did not fire","focalLength":"10mm"}},{"image":{"path":"slides\/SET08605.webp","width":1500,"height":2000},"thumb":{"path":"thumbs\/SET08605.webp","width":512,"height":410},"thumbCaption":"<span class=\"nr\">27<\/span><div class=\"title\">SET08605<\/div>","photodata":"<b>Original Date<\/b> <i>5\/1\/23, 12:01\u202FPM<\/i> &middot; <b>Make<\/b> <i>SONY<\/i> &middot; <b>Camera<\/b> <i>DSC-HX99<\/i> &middot; <b>Lens<\/b> <i>4.25-118mm f\/3.5-6.4<\/i> &middot; <b>Focal Length (35mm)<\/b> <i>32mm<\/i> &middot; <b>Metering Mode<\/b> <i>Multi-segment<\/i> &middot; <b>ISO Equivalent<\/b> <i>200<\/i> &middot; <b>Exposure Time<\/b> <i>1\/200s<\/i> &middot; <b>Aperture<\/b> <i>ƒ\/8<\/i> &middot; <b>Exposure bias<\/b> <i>0 EV<\/i> &middot; <b>Exposure Program<\/b> <i>Manual control<\/i> &middot; <b>White balance<\/b> <i>Auto white balance<\/i> &middot; <b>Flash<\/b> <i>Flash did not fire<\/i> &middot; <b>Resolution<\/b> <i>4896 x 3672<\/i>","dates":{"added":1683998744,"dateTaken":1682931663},"fileDate":"2023-05-01T12:01:02.0Z","path":"SET08605.webp","imageCaption":"<div class=\"title\">SET08605<\/div>","fileSize":18375829,"name":"SET08605.webp","comment":"                               ","location":"48.181424,16.299721","category":"image","camera":{"aperture":8.0,"exposureTime":"1\/200s","originalDate":"2023-05-01T12:01:03.0Z","cameraModel":"DSC-HX99","location":{"latitude":"48° 10' 53.13\"","lat":48.181423,"long":16.29972,"longitude":"16° 17' 59\""},"focalLength35mm":"32mm","resolution":"4896 x 3672","cameraMake":"SONY","isoEquivalent":200,"flash":"Flash did not fire","focalLength":"5mm"}},{"image":{"path":"slides\/SET08606.webp","width":1500,"height":2000},"thumb":{"path":"thumbs\/SET08606.webp","width":512,"height":410},"thumbCaption":"<span class=\"nr\">28<\/span><div class=\"title\">SET08606<\/div>","photodata":"<b>Original Date<\/b> <i>5\/1\/23, 12:01\u202FPM<\/i> &middot; <b>Make<\/b> <i>SONY<\/i> &middot; <b>Camera<\/b> <i>DSC-HX99<\/i> &middot; <b>Lens<\/b> <i>4.25-118mm f\/3.5-6.4<\/i> &middot; <b>Focal Length (35mm)<\/b> <i>43mm<\/i> &middot; <b>Metering Mode<\/b> <i>Multi-segment<\/i> &middot; <b>ISO Equivalent<\/b> <i>200<\/i> &middot; <b>Exposure Time<\/b> <i>1\/200s<\/i> &middot; <b>Aperture<\/b> <i>ƒ\/8<\/i> &middot; <b>Exposure bias<\/b> <i>0 EV<\/i> &middot; <b>Exposure Program<\/b> <i>Manual control<\/i> &middot; <b>White balance<\/b> <i>Auto white balance<\/i> &middot; <b>Flash<\/b> <i>Flash did not fire<\/i> &middot; <b>Resolution<\/b> <i>4896 x 3672<\/i>","dates":{"added":1683998744,"dateTaken":1682931677},"fileDate":"2023-05-01T12:01:16.0Z","path":"SET08606.webp","imageCaption":"<div class=\"title\">SET08606<\/div>","fileSize":14073304,"name":"SET08606.webp","comment":"                               ","location":"48.181446,16.299743","category":"image","camera":{"aperture":8.0,"exposureTime":"1\/200s","originalDate":"2023-05-01T12:01:17.0Z","cameraModel":"DSC-HX99","location":{"latitude":"48° 10' 53.21\"","lat":48.181446,"long":16.299744,"longitude":"16° 17' 59.08\""},"focalLength35mm":"43mm","resolution":"4896 x 3672","cameraMake":"SONY","isoEquivalent":200,"flash":"Flash did not fire","focalLength":"7mm"}},{"image":{"path":"slides\/SET08607.webp","width":2000,"height":1500},"thumb":{"path":"thumbs\/SET08607.webp","width":512,"height":410},"thumbCaption":"<span class=\"nr\">29<\/span><div class=\"title\">SET08607<\/div>","photodata":"<b>Original Date<\/b> <i>5\/1\/23, 12:01\u202FPM<\/i> &middot; <b>Make<\/b> <i>SONY<\/i> &middot; <b>Camera<\/b> <i>DSC-HX99<\/i> &middot; <b>Lens<\/b> <i>4.25-118mm f\/3.5-6.4<\/i> &middot; <b>Focal Length (35mm)<\/b> <i>43mm<\/i> &middot; <b>Metering Mode<\/b> <i>Multi-segment<\/i> &middot; <b>ISO Equivalent<\/b> <i>200<\/i> &middot; <b>Exposure Time<\/b> <i>1\/320s<\/i> &middot; <b>Aperture<\/b> <i>ƒ\/8<\/i> &middot; <b>Exposure bias<\/b> <i>0 EV<\/i> &middot; <b>Exposure Program<\/b> <i>Manual control<\/i> &middot; <b>White balance<\/b> <i>Auto white balance<\/i> &middot; <b>Flash<\/b> <i>Flash did not fire<\/i> &middot; <b>Resolution<\/b> <i>4896 x 3672<\/i>","dates":{"added":1683998744,"dateTaken":1682931698},"fileDate":"2023-05-01T12:01:38.0Z","path":"SET08607.webp","imageCaption":"<div class=\"title\">SET08607<\/div>","fileSize":15013062,"name":"SET08607.webp","comment":"                               ","location":"48.181482,16.299768","category":"image","camera":{"aperture":8.0,"exposureTime":"1\/320s","originalDate":"2023-05-01T12:01:38.0Z","cameraModel":"DSC-HX99","location":{"latitude":"48° 10' 53.33\"","lat":48.18148,"long":16.299768,"longitude":"16° 17' 59.17\""},"focalLength35mm":"43mm","resolution":"4896 x 3672","cameraMake":"SONY","isoEquivalent":200,"flash":"Flash did not fire","focalLength":"7mm"}},{"image":{"path":"slides\/SET08608.webp","width":1500,"height":2000},"thumb":{"path":"thumbs\/SET08608.webp","width":512,"height":410},"thumbCaption":"<span class=\"nr\">30<\/span><div class=\"title\">SET08608<\/div>","photodata":"<b>Original Date<\/b> <i>5\/1\/23, 12:01\u202FPM<\/i> &middot; <b>Make<\/b> <i>SONY<\/i> &middot; <b>Camera<\/b> <i>DSC-HX99<\/i> &middot; <b>Lens<\/b> <i>4.25-118mm f\/3.5-6.4<\/i> &middot; <b>Focal Length (35mm)<\/b> <i>43mm<\/i> &middot; <b>Metering Mode<\/b> <i>Multi-segment<\/i> &middot; <b>ISO Equivalent<\/b> <i>200<\/i> &middot; <b>Exposure Time<\/b> <i>1\/500s<\/i> &middot; <b>Aperture<\/b> <i>ƒ\/8<\/i> &middot; <b>Exposure bias<\/b> <i>0 EV<\/i> &middot; <b>Exposure Program<\/b> <i>Manual control<\/i> &middot; <b>White balance<\/b> <i>Auto white balance<\/i> &middot; <b>Flash<\/b> <i>Flash did not fire<\/i> &middot; <b>Resolution<\/b> <i>4896 x 3672<\/i>","dates":{"added":1683998744,"dateTaken":1682931706},"fileDate":"2023-05-01T12:01:46.0Z","path":"SET08608.webp","imageCaption":"<div class=\"title\">SET08608<\/div>","fileSize":10735791,"name":"SET08608.webp","comment":"                               ","location":"48.181486,16.299771","category":"image","camera":{"aperture":8.0,"exposureTime":"1\/500s","originalDate":"2023-05-01T12:01:46.0Z","cameraModel":"DSC-HX99","location":{"latitude":"48° 10' 53.35\"","lat":48.181484,"long":16.29977,"longitude":"16° 17' 59.17\""},"focalLength35mm":"43mm","resolution":"4896 x 3672","cameraMake":"SONY","isoEquivalent":200,"flash":"Flash did not fire","focalLength":"7mm"}},{"image":{"path":"slides\/SET08609.webp","width":1500,"height":2000},"thumb":{"path":"thumbs\/SET08609.webp","width":512,"height":410},"thumbCaption":"<span class=\"nr\">31<\/span><div class=\"title\">SET08609<\/div>","photodata":"<b>Original Date<\/b> <i>5\/1\/23, 12:01\u202FPM<\/i> &middot; <b>Make<\/b> <i>SONY<\/i> &middot; <b>Camera<\/b> <i>DSC-HX99<\/i> &middot; <b>Lens<\/b> <i>4.25-118mm f\/3.5-6.4<\/i> &middot; <b>Focal Length (35mm)<\/b> <i>43mm<\/i> &middot; <b>Metering Mode<\/b> <i>Multi-segment<\/i> &middot; <b>ISO Equivalent<\/b> <i>200<\/i> &middot; <b>Exposure Time<\/b> <i>1\/500s<\/i> &middot; <b>Aperture<\/b> <i>ƒ\/8<\/i> &middot; <b>Exposure bias<\/b> <i>0 EV<\/i> &middot; <b>Exposure Program<\/b> <i>Manual control<\/i> &middot; <b>White balance<\/b> <i>Auto white balance<\/i> &middot; <b>Flash<\/b> <i>Flash did not fire<\/i> &middot; <b>Resolution<\/b> <i>4896 x 3672<\/i>","dates":{"added":1683998744,"dateTaken":1682931711},"fileDate":"2023-05-01T12:01:50.0Z","path":"SET08609.webp","imageCaption":"<div class=\"title\">SET08609<\/div>","fileSize":11824077,"name":"SET08609.webp","comment":"                               ","location":"48.181479,16.299812","category":"image","camera":{"aperture":8.0,"exposureTime":"1\/500s","originalDate":"2023-05-01T12:01:51.0Z","cameraModel":"DSC-HX99","location":{"latitude":"48° 10' 53.33\"","lat":48.18148,"long":16.299812,"longitude":"16° 17' 59.32\""},"focalLength35mm":"43mm","resolution":"4896 x 3672","cameraMake":"SONY","isoEquivalent":200,"flash":"Flash did not fire","focalLength":"7mm"}},{"image":{"path":"slides\/SET08610.webp","width":1500,"height":2000},"thumb":{"path":"thumbs\/SET08610.webp","width":512,"height":410},"thumbCaption":"<span class=\"nr\">32<\/span><div class=\"title\">SET08610<\/div>","photodata":"<b>Original Date<\/b> <i>5\/1\/23, 12:01\u202FPM<\/i> &middot; <b>Make<\/b> <i>SONY<\/i> &middot; <b>Camera<\/b> <i>DSC-HX99<\/i> &middot; <b>Lens<\/b> <i>4.25-118mm f\/3.5-6.4<\/i> &middot; <b>Focal Length (35mm)<\/b> <i>88mm<\/i> &middot; <b>Metering Mode<\/b> <i>Multi-segment<\/i> &middot; <b>ISO Equivalent<\/b> <i>200<\/i> &middot; <b>Exposure Time<\/b> <i>1\/500s<\/i> &middot; <b>Aperture<\/b> <i>ƒ\/8<\/i> &middot; <b>Exposure bias<\/b> <i>0 EV<\/i> &middot; <b>Exposure Program<\/b> <i>Manual control<\/i> &middot; <b>White balance<\/b> <i>Auto white balance<\/i> &middot; <b>Flash<\/b> <i>Flash did not fire<\/i> &middot; <b>Resolution<\/b> <i>4896 x 3672<\/i>","dates":{"added":1683998744,"dateTaken":1682931718},"fileDate":"2023-05-01T12:01:58.0Z","path":"SET08610.webp","imageCaption":"<div class=\"title\">SET08610<\/div>","fileSize":12635146,"name":"SET08610.webp","comment":"                               ","location":"48.181450,16.299802","category":"image","camera":{"aperture":8.0,"exposureTime":"1\/500s","originalDate":"2023-05-01T12:01:58.0Z","cameraModel":"DSC-HX99","location":{"latitude":"48° 10' 53.22\"","lat":48.18145,"long":16.299803,"longitude":"16° 17' 59.29\""},"focalLength35mm":"88mm","resolution":"4896 x 3672","cameraMake":"SONY","isoEquivalent":200,"flash":"Flash did not fire","focalLength":"14mm"}},{"image":{"path":"slides\/SET08611.webp","width":2000,"height":1500},"thumb":{"path":"thumbs\/SET08611.webp","width":512,"height":410},"thumbCaption":"<span class=\"nr\">33<\/span><div class=\"title\">SET08611<\/div>","photodata":"<b>Original Date<\/b> <i>5\/1\/23, 12:02\u202FPM<\/i> &middot; <b>Make<\/b> <i>SONY<\/i> &middot; <b>Camera<\/b> <i>DSC-HX99<\/i> &middot; <b>Lens<\/b> <i>4.25-118mm f\/3.5-6.4<\/i> &middot; <b>Focal Length (35mm)<\/b> <i>88mm<\/i> &middot; <b>Metering Mode<\/b> <i>Multi-segment<\/i> &middot; <b>ISO Equivalent<\/b> <i>200<\/i> &middot; <b>Exposure Time<\/b> <i>1\/500s<\/i> &middot; <b>Aperture<\/b> <i>ƒ\/8<\/i> &middot; <b>Exposure bias<\/b> <i>0 EV<\/i> &middot; <b>Exposure Program<\/b> <i>Manual control<\/i> &middot; <b>White balance<\/b> <i>Auto white balance<\/i> &middot; <b>Flash<\/b> <i>Flash did not fire<\/i> &middot; <b>Resolution<\/b> <i>4896 x 3672<\/i>","dates":{"added":1683998744,"dateTaken":1682931723},"fileDate":"2023-05-01T12:02:02.0Z","path":"SET08611.webp","imageCaption":"<div class=\"title\">SET08611<\/div>","fileSize":13327737,"name":"SET08611.webp","comment":"                               ","location":"48.181443,16.299825","category":"image","camera":{"aperture":8.0,"exposureTime":"1\/500s","originalDate":"2023-05-01T12:02:03.0Z","cameraModel":"DSC-HX99","location":{"latitude":"48° 10' 53.2\"","lat":48.181442,"long":16.299826,"longitude":"16° 17' 59.37\""},"focalLength35mm":"88mm","resolution":"4896 x 3672","cameraMake":"SONY","isoEquivalent":200,"flash":"Flash did not fire","focalLength":"14mm"}},{"image":{"path":"slides\/SET08612.webp","width":2000,"height":1500},"thumb":{"path":"thumbs\/SET08612.webp","width":512,"height":410},"thumbCaption":"<span class=\"nr\">34<\/span><div class=\"title\">SET08612<\/div>","photodata":"<b>Original Date<\/b> <i>5\/1\/23, 12:02\u202FPM<\/i> &middot; <b>Make<\/b> <i>SONY<\/i> &middot; <b>Camera<\/b> <i>DSC-HX99<\/i> &middot; <b>Lens<\/b> <i>4.25-118mm f\/3.5-6.4<\/i> &middot; <b>Focal Length (35mm)<\/b> <i>88mm<\/i> &middot; <b>Metering Mode<\/b> <i>Multi-segment<\/i> &middot; <b>ISO Equivalent<\/b> <i>200<\/i> &middot; <b>Exposure Time<\/b> <i>1\/400s<\/i> &middot; <b>Aperture<\/b> <i>ƒ\/8<\/i> &middot; <b>Exposure bias<\/b> <i>0 EV<\/i> &middot; <b>Exposure Program<\/b> <i>Manual control<\/i> &middot; <b>White balance<\/b> <i>Auto white balance<\/i> &middot; <b>Flash<\/b> <i>Flash did not fire<\/i> &middot; <b>Resolution<\/b> <i>4896 x 3672<\/i>","dates":{"added":1683998744,"dateTaken":1682931728},"fileDate":"2023-05-01T12:02:08.0Z","path":"SET08612.webp","imageCaption":"<div class=\"title\">SET08612<\/div>","fileSize":11896436,"name":"SET08612.webp","comment":"                               ","location":"48.181454,16.299842","category":"image","camera":{"aperture":8.0,"exposureTime":"1\/400s","originalDate":"2023-05-01T12:02:08.0Z","cameraModel":"DSC-HX99","location":{"latitude":"48° 10' 53.23\"","lat":48.181454,"long":16.299843,"longitude":"16° 17' 59.43\""},"focalLength35mm":"88mm","resolution":"4896 x 3672","cameraMake":"SONY","isoEquivalent":200,"flash":"Flash did not fire","focalLength":"14mm"}},{"image":{"path":"slides\/SET08613.webp","width":2000,"height":1500},"thumb":{"path":"thumbs\/SET08613.webp","width":512,"height":410},"thumbCaption":"<span class=\"nr\">35<\/span><div class=\"title\">SET08613<\/div>","photodata":"<b>Original Date<\/b> <i>5\/1\/23, 12:02\u202FPM<\/i> &middot; <b>Make<\/b> <i>SONY<\/i> &middot; <b>Camera<\/b> <i>DSC-HX99<\/i> &middot; <b>Lens<\/b> <i>4.25-118mm f\/3.5-6.4<\/i> &middot; <b>Focal Length (35mm)<\/b> <i>62mm<\/i> &middot; <b>Metering Mode<\/b> <i>Multi-segment<\/i> &middot; <b>ISO Equivalent<\/b> <i>200<\/i> &middot; <b>Exposure Time<\/b> <i>1\/400s<\/i> &middot; <b>Aperture<\/b> <i>ƒ\/8<\/i> &middot; <b>Exposure bias<\/b> <i>0 EV<\/i> &middot; <b>Exposure Program<\/b> <i>Manual control<\/i> &middot; <b>White balance<\/b> <i>Auto white balance<\/i> &middot; <b>Flash<\/b> <i>Flash did not fire<\/i> &middot; <b>Resolution<\/b> <i>4896 x 3672<\/i>","dates":{"added":1683998744,"dateTaken":1682931736},"fileDate":"2023-05-01T12:02:16.0Z","path":"SET08613.webp","imageCaption":"<div class=\"title\">SET08613<\/div>","fileSize":15927313,"name":"SET08613.webp","comment":"                               ","location":"48.181467,16.299783","category":"image","camera":{"aperture":8.0,"exposureTime":"1\/400s","originalDate":"2023-05-01T12:02:16.0Z","cameraModel":"DSC-HX99","location":{"latitude":"48° 10' 53.28\"","lat":48.181465,"long":16.299784,"longitude":"16° 17' 59.22\""},"focalLength35mm":"62mm","resolution":"4896 x 3672","cameraMake":"SONY","isoEquivalent":200,"flash":"Flash did not fire","focalLength":"10mm"}}],"name":"Клекачка перистая - Staphylea pinnata","dates":{"added":1683998744,"dateRange":{"0":1432462608,"1":1682931736}},"fileDate":"2023-05-13T20:03:20.979Z"}